Projeto 2 Final/Projeto2_Microondas/Projeto2_Microondas/microondas_nivel1/timer_nivel2/nivel3/HDL/contador_mod_10.v
module Counter_mod_10(output wire [3:0] ones, 
                      output wire tc,zero, 
                      input wire clk, clearn, EN, loadn,
                      input wire [3:0] data);

  // Registradores para que seja possível realizar a atribuição, que é feita de forma sequencial
  // dentro do bloco always
  reg [3:0] current_state;
  assign ones = current_state;
  // O zero só pode ser 1 quando o estado atual desse contador é 0, ou seja, quando ele tiver
  // chegado em 0
  assign zero = (current_state == 0) ? 1 : 0;
  // O tc só pode ser 1 quando o contador tiver chegado a 0 e o enable for 1
  assign tc = ((current_state == 0)& EN) ? 1 : 0;

  always @(posedge clk)
    begin
      if (EN) begin
        if (current_state == 4'b0000) begin
          // Se o contador chegar a zero, reinicia a contagem
          current_state <= 4'b1001;
        end
        else begin
          // Se o contador ainda não for 0, diminui em 1 unidade
          current_state <= current_state - 1;
        end
      end
      else begin
        if (!loadn) begin
          current_state <= data;
        end
      end
    end
  // O próximo always verifica o clear de forma assíncrona, para zerar o contador caso a tecla seja
  // apertada
  always @(negedge clearn) begin
    if (!clearn) begin
      current_state <= 4'b0000;
    end
  end
endmodule

Projeto 2 Final/Projeto2_Microondas/Projeto2_Microondas/microondas_nivel1/timer_nivel2/nivel3/Teste/contador_mod_10_tb.v
`timescale 1ns/1ps
`include "../HDL/contador_mod_10.v"

module Counter_mod_10_tb();

    reg [3:0] data_tb;
    reg clk_tb, clearn_tb, EN_tb, loadn_tb;
    wire [3:0] ones_tb;
    
    Counter_mod_10 UUT(.data(data_tb), .clk(clk_tb), .clearn(clearn_tb), .EN(EN_tb), .loadn(loadn_tb));
    
    // Testa vários possível casos de entrada para o contador_mod_10

    initial 
        begin
            $dumpfile("contador_mod_10_tb.vcd");
            $dumpvars(0, Counter_mod_10_tb);

                clk_tb=0; clearn_tb=1; EN_tb=1; loadn_tb=0; data_tb=0;
            #10 clk_tb=1; clearn_tb=1; EN_tb=1; loadn_tb=0; data_tb=9;
            #10 clk_tb=0; clearn_tb=1; EN_tb=1; loadn_tb=1; data_tb=9;
            #10 clk_tb=1; clearn_tb=0; EN_tb=1; loadn_tb=1; data_tb=0;
            #10 clk_tb=0; clearn_tb=1; EN_tb=1; loadn_tb=1; data_tb=0;
            #10 clk_tb=1; clearn_tb=1; EN_tb=1; loadn_tb=1; data_tb=0;
            #10 clk_tb=0; clearn_tb=1; EN_tb=1; loadn_tb=1; data_tb=0;
            #10 clk_tb=1; clearn_tb=1; EN_tb=1; loadn_tb=1; data_tb=0;
            #10 clk_tb=0; clearn_tb=1; EN_tb=1; loadn_tb=1; data_tb=0;
            #10 clk_tb=1; clearn_tb=1; EN_tb=1; loadn_tb=1; data_tb=0;
            #10 clk_tb=0; clearn_tb=1; EN_tb=1; loadn_tb=1; data_tb=0;
            #10 clk_tb=1; clearn_tb=1; EN_tb=1; loadn_tb=1; data_tb=0;
            #10 clk_tb=0; clearn_tb=1; EN_tb=1; loadn_tb=1; data_tb=0;
            #10 clk_tb=1; clearn_tb=1; EN_tb=1; loadn_tb=1; data_tb=0;
            #10 clk_tb=0; clearn_tb=1; EN_tb=1; loadn_tb=1; data_tb=0;
            #10 clk_tb=1; clearn_tb=1; EN_tb=1; loadn_tb=1; data_tb=0;
            #10 clk_tb=0; clearn_tb=1; EN_tb=1; loadn_tb=1; data_tb=0;
            #10 clk_tb=1; clearn_tb=1; EN_tb=1; loadn_tb=1; data_tb=0;
            #10 clk_tb=0; clearn_tb=1; EN_tb=1; loadn_tb=1; data_tb=0;
            #10 clk_tb=1; clearn_tb=1; EN_tb=1; loadn_tb=1; data_tb=0;
            #10 clk_tb=0; clearn_tb=1; EN_tb=1; loadn_tb=1; data_tb=0;
            #10 clk_tb=1; clearn_tb=1; EN_tb=1; loadn_tb=1; data_tb=0;
            #10 clk_tb=0; clearn_tb=1; EN_tb=1; loadn_tb=1; data_tb=0;
            #10 clk_tb=1; clearn_tb=1; EN_tb=1; loadn_tb=1; data_tb=0;
            #10 clk_tb=0; clearn_tb=1; EN_tb=1; loadn_tb=1; data_tb=0;
            #10 clk_tb=1; clearn_tb=1; EN_tb=1; loadn_tb=1; data_tb=0;
            #10 clk_tb=0; clearn_tb=1; EN_tb=1; loadn_tb=1; data_tb=0;
            #10 clk_tb=1; clearn_tb=1; EN_tb=1; loadn_tb=1; data_tb=0;
            #10 clk_tb=0; clearn_tb=1; EN_tb=1; loadn_tb=1; data_tb=0;
            #10 clk_tb=1; clearn_tb=1; EN_tb=1; loadn_tb=1; data_tb=0;
            #10 clk_tb=0; clearn_tb=1; EN_tb=1; loadn_tb=1; data_tb=0;
            #10 clk_tb=1; clearn_tb=1; EN_tb=1; loadn_tb=1; data_tb=0;
            #10 clk_tb=0; clearn_tb=1; EN_tb=1; loadn_tb=1; data_tb=0;
            
            #10;
        end
endmodule

Projeto 2 Final/Projeto2_Microondas/Projeto2_Microondas/microondas_nivel1/timer_nivel2/nivel3/Teste/contador_mod_10_tb.vcd
$date
	Sat Jul 23 17:09:12 2022
$end
$version
	Icarus Verilog
$end
$timescale
	1ps
$end
$scope module Counter_mod_10_tb $end
$var reg 1 ! EN_tb $end
$var reg 1 " clearn_tb $end
$var reg 1 # clk_tb $end
$var reg 4 $ data_tb [3:0] $end
$var reg 1 % loadn_tb $end
$scope module UUT $end
$var wire 1 ! EN $end
$var wire 1 " clearn $end
$var wire 1 # clk $end
$var wire 4 & data [3:0] $end
$var wire 1 % loadn $end
$var wire 4 ' ones [3:0] $end
$var wire 1 ( zero $end
$var wire 1 ) tc $end
$var reg 4 * current_state [3:0] $end
$upscope $end
$upscope $end
$enddefinitions $end
#0
$dumpvars
bx *
x)
x(
bx '
b0 &
0%
b0 $
0#
1"
1!
$end
#10000
b1001 $
b1001 &
1#
#20000
1%
0#
#30000
1)
1(
b0 '
b0 *
b0 $
b0 &
0"
1#
#40000
1"
0#
#50000
0)
0(
b1001 '
b1001 *
1#
#60000
0#
#70000
b1000 '
b1000 *
1#
#80000
0#
#90000
b111 '
b111 *
1#
#100000
0#
#110000
b110 '
b110 *
1#
#120000
0#
#130000
b101 '
b101 *
1#
#140000
0#
#150000
b100 '
b100 *
1#
#160000
0#
#170000
b11 '
b11 *
1#
#180000
0#
#190000
b10 '
b10 *
1#
#200000
0#
#210000
b1 '
b1 *
1#
#220000
0#
#230000
1)
1(
b0 '
b0 *
1#
#240000
0#
#250000
0)
0(
b1001 '
b1001 *
1#
#260000
0#
#270000
b1000 '
b1000 *
1#
#280000
0#
#290000
b111 '
b111 *
1#
#300000
0#
#310000
b110 '
b110 *
1#
