luiza-diniz/Nivel1/Control_Input/modulos_nivel3/mux_2to1.v
module mux_2to1 (input wire sel, A, B,output wire F);

    assign F = (sel == 1'b0) ? A : B;

endmodule

luiza-diniz/Nivel1/Control_Input/modulos_nivel3/count_mod8.v
module counter_mod8 (input wire clearn,input wire clock,output reg F);

    reg [2:0] count;

    reg active_count;

    always @(posedge clearn) begin
        active_count = 1'b0;
    end

    always @ (negedge clearn) begin
        count <= 3'b000;
        F <= 1'b0;
        active_count = 1'b1;
    end

    always @(posedge clock) begin
        if (active_count) begin
            case (count)
                3'b000: count <= 3'b001;
                3'b001: count <= 3'b010;
                3'b010: count <= 3'b011;
                3'b011: begin
                    count <= 3'b100;
                    F = 1'b1;
                end
                3'b100: count <= 3'b101;
                3'b101: count <= 3'b110;
                3'b110: count <= 3'b111;
                default: count <= count;
            endcase
        end
    end
endmodule

luiza-diniz/Nivel1/Control_Input/modulos_nivel3/encoder.v
module encoder (input wire [9:0] keypad,input wire en,output wire [3:0] BCD,output reg data_valid);

    assign BCD = (keypad == 10'b0000_000_001 && !en) ? 4'b0000 :
                 (keypad == 10'b0000_000_010 && !en) ? 4'b0001 :
                 (keypad == 10'b0000_000_100 && !en) ? 4'b0010 :
                 (keypad == 10'b0000_001_000 && !en) ? 4'b0011 :
                 (keypad == 10'b0000_010_000 && !en) ? 4'b0100 :
                 (keypad == 10'b0000_100_000 && !en) ? 4'b0101 :
                 (keypad == 10'b0001_000_000 && !en) ? 4'b0110 :
                 (keypad == 10'b0010_000_000 && !en) ? 4'b0111 :
                 (keypad == 10'b0100_000_000 && !en) ? 4'b1000 :
                 (keypad == 10'b1000_000_000 && !en) ? 4'b1001 :
                 4'bXXXX;

    always @(keypad, en) begin
        if ((keypad == 10'b0000_000_000) || en) data_valid = 1'b1; 
        else data_valid = 1'b0;
    end
    
endmodule

luiza-diniz/Nivel1/Control_Input/modulos_nivel3/div100.v
module div100 (input wire clock, clearn,output reg clock_div100);

    integer aux = 0;

    always @(posedge clearn) begin
        aux = 0;
    end

    always @(posedge clock) begin
        if (aux == 100) begin
           clock_div100 = 1'b1;
           aux = 0; 
        end
        else clock_div100 = 1'b0;
        aux = aux + 1;
    end

endmodule

luiza-diniz/Nivel1/Control_Input/control_input.v
`include "Control_Input/modulos_nivel3/count_mod8.v"
`include "Control_Input/modulos_nivel3/div100.v"
`include "Control_Input/modulos_nivel3/encoder.v"
`include "Control_Input/modulos_nivel3/mux_2to1.v"

module control_input (input wire [9:0] keypad,input wire clock, en,

    output wire [3:0] BCD,
    output wire loadn, pgt_1Hz);

    wire clock_div100, F;

    div100  div100(.clock(clock), .clearn(en),.clock_div100(clock_div100));

    encoder encoder(.keypad(keypad), .en(en),.BCD(BCD), .data_valid(loadn));

    counter_mod8 counter(.clearn(loadn), .clock(clock),.F(F));

    mux_2to1 mux(.sel(en), .A(F), .B(clock_div100),.F(pgt_1Hz));

endmodule

luiza-diniz/Nivel1/Control_Input/control_input_TB.v
`timescale 1us/1ps

module control_input_TB ();

    reg [9:0] keypad_TB;
    reg en_TB, clock_TB;
    wire [3:0] BCD_TB;
    wire loadn_TB, pgt_1Hz_TB;

    control_input DUT(.BCD(BCD_TB), .loadn(loadn_TB), .pgt_1Hz(pgt_1Hz_TB), .keypad(keypad_TB), .en(en_TB), .clock(clock_TB));

    integer i;

    initial begin
        $dumpfile("control_input_TB.vcd");
        $dumpvars(0,control_input_TB);

        for(i = 0; i < 2500; i = i+1) begin
            #5000 clock_TB <= !clock_TB;
        end
    end 

    initial begin
        clock_TB = 1'b1;
        keypad_TB = 10'b0000_000_001; en_TB = 1'b1;
        #100000 en_TB = 1'b0;
        #100000 keypad_TB = 10'b0000_000_000;
        #100000 keypad_TB = 10'b0000_010_000;
        #100000 keypad_TB = 10'b0000_000_000;
        #100000 keypad_TB = 10'b1000_000_000;
        #25000 en_TB = 1'b1;
    end 
endmodule

luiza-diniz/Nivel1/control_input_TB.vcd
$date
	Thu May 12 21:21:54 2022
$end
$version
	Icarus Verilog
$end
$timescale
	1ps
$end
$scope module control_input_TB $end
$var wire 1 ! pgt_1Hz_TB $end
$var wire 1 " loadn_TB $end
$var wire 4 # BCD_TB [3:0] $end
$var reg 1 $ clock_TB $end
$var reg 1 % en_TB $end
$var reg 10 & keypad_TB [9:0] $end
$var integer 32 ' i [31:0] $end
$scope module DUT $end
$var wire 1 $ clock $end
$var wire 1 % en $end
$var wire 10 ( keypad [9:0] $end
$var wire 1 ! pgt_1Hz $end
$var wire 1 " loadn $end
$var wire 1 ) clock_div100 $end
$var wire 1 * F $end
$var wire 4 + BCD [3:0] $end
$scope module counter $end
$var wire 1 $ clock $end
$var wire 1 " clearn $end
$var reg 1 * F $end
$var reg 1 , active_count $end
$var reg 3 - count [2:0] $end
$upscope $end
$scope module div100 $end
$var wire 1 % clearn $end
$var wire 1 $ clock $end
$var reg 1 ) clock_div100 $end
$var integer 32 . aux [31:0] $end
$upscope $end
$scope module encoder $end
$var wire 1 % en $end
$var wire 10 / keypad [9:0] $end
$var wire 4 0 BCD [3:0] $end
$var reg 1 " data_valid $end
$upscope $end
$scope module mux $end
$var wire 1 * A $end
$var wire 1 ) B $end
$var wire 1 % sel $end
$var wire 1 ! F $end
$upscope $end
$upscope $end
$upscope $end
$enddefinitions $end
#0
$dumpvars
bx 0
b1 /
b0 .
bx -
0,
bx +
x*
0)
b1 (
b0 '
b1 &
1%
1$
bx #
1"
0!
$end
#5000000000
0$
b1 '
#10000000000
b1 .
1$
b10 '
#15000000000
0$
b11 '
#20000000000
b10 .
1$
b100 '
#25000000000
0$
b101 '
#30000000000
b11 .
1$
b110 '
#35000000000
0$
b111 '
#40000000000
b100 .
1$
b1000 '
#45000000000
0$
b1001 '
#50000000000
b101 .
1$
b1010 '
#55000000000
0$
b1011 '
#60000000000
b110 .
1$
b1100 '
#65000000000
0$
b1101 '
#70000000000
b111 .
1$
b1110 '
#75000000000
0$
b1111 '
#80000000000
b1000 .
1$
b10000 '
#85000000000
0$
b10001 '
#90000000000
b1001 .
1$
b10010 '
#95000000000
0$
b10011 '
#100000000000
b1010 .
0*
b1 -
1$
1,
b0 #
b0 +
b0 0
0!
0"
b10100 '
0%
#105000000000
0$
b10101 '
#110000000000
b10 -
b1011 .
1$
b10110 '
#115000000000
0$
b10111 '
#120000000000
b11 -
b1100 .
1$
b11000 '
#125000000000
0$
b11001 '
#130000000000
b100 -
1!
1*
b1101 .
1$
b11010 '
#135000000000
0$
b11011 '
#140000000000
b101 -
b1110 .
1$
b11100 '
#145000000000
0$
b11101 '
#150000000000
b110 -
b1111 .
1$
b11110 '
#155000000000
0$
b11111 '
#160000000000
b111 -
b10000 .
1$
b100000 '
#165000000000
0$
b100001 '
#170000000000
b10001 .
1$
b100010 '
#175000000000
0$
b100011 '
#180000000000
b10010 .
1$
b100100 '
#185000000000
0$
b100101 '
#190000000000
b10011 .
1$
b100110 '
#195000000000
0$
b100111 '
#200000000000
b10100 .
1$
0,
bx #
bx +
bx 0
1"
b101000 '
b0 &
b0 (
b0 /
#205000000000
0$
b101001 '
#210000000000
b10101 .
1$
b101010 '
#215000000000
0$
b101011 '
#220000000000
b10110 .
1$
b101100 '
#225000000000
0$
b101101 '
#230000000000
b10111 .
1$
b101110 '
#235000000000
0$
b101111 '
#240000000000
b11000 .
1$
b110000 '
#245000000000
0$
b110001 '
#250000000000
b11001 .
1$
b110010 '
#255000000000
0$
b110011 '
#260000000000
b11010 .
1$
b110100 '
#265000000000
0$
b110101 '
#270000000000
b11011 .
1$
b110110 '
#275000000000
0$
b110111 '
#280000000000
b11100 .
1$
b111000 '
#285000000000
0$
b111001 '
#290000000000
b11101 .
1$
b111010 '
#295000000000
0$
b111011 '
#300000000000
0!
b11110 .
0*
b1 -
1$
b100 #
b100 +
b100 0
1,
0"
b111100 '
b10000 &
b10000 (
b10000 /
#305000000000
0$
b111101 '
#310000000000
b10 -
b11111 .
1$
b111110 '
#315000000000
0$
b111111 '
#320000000000
b11 -
b100000 .
1$
b1000000 '
#325000000000
0$
b1000001 '
#330000000000
b100 -
1!
1*
b100001 .
1$
b1000010 '
#335000000000
0$
b1000011 '
#340000000000
b101 -
b100010 .
1$
b1000100 '
#345000000000
0$
b1000101 '
#350000000000
b110 -
b100011 .
1$
b1000110 '
#355000000000
0$
b1000111 '
#360000000000
b111 -
b100100 .
1$
b1001000 '
#365000000000
0$
b1001001 '
#370000000000
b100101 .
1$
b1001010 '
#375000000000
0$
b1001011 '
#380000000000
b100110 .
1$
b1001100 '
#385000000000
0$
b1001101 '
#390000000000
b100111 .
1$
b1001110 '
#395000000000
0$
b1001111 '
#400000000000
b101000 .
1$
bx #
bx +
bx 0
0,
1"
b1010000 '
b0 &
b0 (
b0 /
#405000000000
0$
b1010001 '
#410000000000
b101001 .
1$
b1010010 '
#415000000000
0$
b1010011 '
#420000000000
b101010 .
1$
b1010100 '
#425000000000
0$
b1010101 '
#430000000000
b101011 .
1$
b1010110 '
#435000000000
0$
b1010111 '
#440000000000
b101100 .
1$
b1011000 '
#445000000000
0$
b1011001 '
#450000000000
b101101 .
1$
b1011010 '
#455000000000
0$
b1011011 '
#460000000000
b101110 .
1$
b1011100 '
#465000000000
0$
b1011101 '
#470000000000
b101111 .
1$
b1011110 '
#475000000000
0$
b1011111 '
#480000000000
b110000 .
1$
b1100000 '
#485000000000
0$
b1100001 '
#490000000000
b110001 .
1$
b1100010 '
#495000000000
0$
b1100011 '
#500000000000
0!
b110010 .
0*
b1 -
1$
b1001 #
b1001 +
b1001 0
1,
0"
b1100100 '
b1000000000 &
b1000000000 (
b1000000000 /
#505000000000
0$
b1100101 '
#510000000000
b10 -
b110011 .
1$
b1100110 '
#515000000000
0$
b1100111 '
#520000000000
b11 -
b110100 .
1$
b1101000 '
#525000000000
0$
bx #
bx +
bx 0
0,
b0 .
1"
b1101001 '
1%
#530000000000
b1 .
1$
b1101010 '
#535000000000
0$
b1101011 '
#540000000000
b10 .
1$
b1101100 '
#545000000000
0$
b1101101 '
#550000000000
b11 .
1$
b1101110 '
#555000000000
0$
b1101111 '
#560000000000
b100 .
1$
b1110000 '
#565000000000
0$
b1110001 '
#570000000000
b101 .
1$
b1110010 '
#575000000000
0$
b1110011 '
#580000000000
b110 .
1$
b1110100 '
#585000000000
0$
b1110101 '
#590000000000
b111 .
1$
b1110110 '
#595000000000
0$
b1110111 '
#600000000000
b1000 .
1$
b1111000 '
#605000000000
0$
b1111001 '
#610000000000
b1001 .
1$
b1111010 '
#615000000000
0$
b1111011 '
#620000000000
b1010 .
1$
b1111100 '
#625000000000
0$
b1111101 '
#630000000000
b1011 .
1$
b1111110 '
#635000000000
0$
b1111111 '
#640000000000
b1100 .
1$
b10000000 '
#645000000000
0$
b10000001 '
#650000000000
b1101 .
1$
b10000010 '
#655000000000
0$
b10000011 '
#660000000000
b1110 .
1$
b10000100 '
#665000000000
0$
b10000101 '
#670000000000
b1111 .
1$
b10000110 '
#675000000000
0$
b10000111 '
#680000000000
b10000 .
1$
b10001000 '
#685000000000
0$
b10001001 '
#690000000000
b10001 .
1$
b10001010 '
#695000000000
0$
b10001011 '
#700000000000
b10010 .
1$
b10001100 '
#705000000000
0$
b10001101 '
#710000000000
b10011 .
1$
b10001110 '
#715000000000
0$
b10001111 '
#720000000000
b10100 .
1$
b10010000 '
#725000000000
0$
b10010001 '
#730000000000
b10101 .
1$
b10010010 '
#735000000000
0$
b10010011 '
#740000000000
b10110 .
1$
b10010100 '
#745000000000
0$
b10010101 '
#750000000000
b10111 .
1$
b10010110 '
#755000000000
0$
b10010111 '
#760000000000
b11000 .
1$
b10011000 '
#765000000000
0$
b10011001 '
#770000000000
b11001 .
1$
b10011010 '
#775000000000
0$
b10011011 '
#780000000000
b11010 .
1$
b10011100 '
#785000000000
0$
b10011101 '
#790000000000
b11011 .
1$
b10011110 '
#795000000000
0$
b10011111 '
#800000000000
b11100 .
1$
b10100000 '
#805000000000
0$
b10100001 '
#810000000000
b11101 .
1$
b10100010 '
#815000000000
0$
b10100011 '
#820000000000
b11110 .
1$
b10100100 '
#825000000000
0$
b10100101 '
#830000000000
b11111 .
1$
b10100110 '
#835000000000
0$
b10100111 '
#840000000000
b100000 .
1$
b10101000 '
#845000000000
0$
b10101001 '
#850000000000
b100001 .
1$
b10101010 '
#855000000000
0$
b10101011 '
#860000000000
b100010 .
1$
b10101100 '
#865000000000
0$
b10101101 '
#870000000000
b100011 .
1$
b10101110 '
#875000000000
0$
b10101111 '
#880000000000
b100100 .
1$
b10110000 '
#885000000000
0$
b10110001 '
#890000000000
b100101 .
1$
b10110010 '
#895000000000
0$
b10110011 '
#900000000000
b100110 .
1$
b10110100 '
#905000000000
0$
b10110101 '
#910000000000
b100111 .
1$
b10110110 '
#915000000000
0$
b10110111 '
#920000000000
b101000 .
1$
b10111000 '
#925000000000
0$
b10111001 '
#930000000000
b101001 .
1$
b10111010 '
#935000000000
0$
b10111011 '
#940000000000
b101010 .
1$
b10111100 '
#945000000000
0$
b10111101 '
#950000000000
b101011 .
1$
b10111110 '
#955000000000
0$
b10111111 '
#960000000000
b101100 .
1$
b11000000 '
#965000000000
0$
b11000001 '
#970000000000
b101101 .
1$
b11000010 '
#975000000000
0$
b11000011 '
#980000000000
b101110 .
1$
b11000100 '
#985000000000
0$
b11000101 '
#990000000000
b101111 .
1$
b11000110 '
#995000000000
0$
b11000111 '
#1000000000000
b110000 .
1$
b11001000 '
#1005000000000
0$
b11001001 '
#1010000000000
b110001 .
1$
b11001010 '
#1015000000000
0$
b11001011 '
#1020000000000
b110010 .
1$
b11001100 '
#1025000000000
0$
b11001101 '
#1030000000000
b110011 .
1$
b11001110 '
#1035000000000
0$
b11001111 '
#1040000000000
b110100 .
1$
b11010000 '
#1045000000000
0$
b11010001 '
#1050000000000
b110101 .
1$
b11010010 '
#1055000000000
0$
b11010011 '
#1060000000000
b110110 .
1$
b11010100 '
#1065000000000
0$
b11010101 '
#1070000000000
b110111 .
1$
b11010110 '
#1075000000000
0$
b11010111 '
#1080000000000
b111000 .
1$
b11011000 '
#1085000000000
0$
b11011001 '
#1090000000000
b111001 .
1$
b11011010 '
#1095000000000
0$
b11011011 '
#1100000000000
b111010 .
1$
b11011100 '
#1105000000000
0$
b11011101 '
#1110000000000
b111011 .
1$
b11011110 '
#1115000000000
0$
b11011111 '
#1120000000000
b111100 .
1$
b11100000 '
#1125000000000
0$
b11100001 '
#1130000000000
b111101 .
1$
b11100010 '
#1135000000000
0$
b11100011 '
#1140000000000
b111110 .
1$
b11100100 '
#1145000000000
0$
b11100101 '
#1150000000000
b111111 .
1$
b11100110 '
#1155000000000
0$
b11100111 '
#1160000000000
b1000000 .
1$
b11101000 '
#1165000000000
0$
b11101001 '
#1170000000000
b1000001 .
1$
b11101010 '
#1175000000000
0$
b11101011 '
#1180000000000
b1000010 .
1$
b11101100 '
#1185000000000
0$
b11101101 '
#1190000000000
b1000011 .
1$
b11101110 '
#1195000000000
0$
b11101111 '
#1200000000000
b1000100 .
1$
b11110000 '
#1205000000000
0$
b11110001 '
#1210000000000
b1000101 .
1$
b11110010 '
#1215000000000
0$
b11110011 '
#1220000000000
b1000110 .
1$
b11110100 '
#1225000000000
0$
b11110101 '
#1230000000000
b1000111 .
1$
b11110110 '
#1235000000000
0$
b11110111 '
#1240000000000
b1001000 .
1$
b11111000 '
#1245000000000
0$
b11111001 '
#1250000000000
b1001001 .
1$
b11111010 '
#1255000000000
0$
b11111011 '
#1260000000000
b1001010 .
1$
b11111100 '
#1265000000000
0$
b11111101 '
#1270000000000
b1001011 .
1$
b11111110 '
#1275000000000
0$
b11111111 '
#1280000000000
b1001100 .
1$
b100000000 '
#1285000000000
0$
b100000001 '
#1290000000000
b1001101 .
1$
b100000010 '
#1295000000000
0$
b100000011 '
#1300000000000
b1001110 .
1$
b100000100 '
#1305000000000
0$
b100000101 '
#1310000000000
b1001111 .
1$
b100000110 '
#1315000000000
0$
b100000111 '
#1320000000000
b1010000 .
1$
b100001000 '
#1325000000000
0$
b100001001 '
#1330000000000
b1010001 .
1$
b100001010 '
#1335000000000
0$
b100001011 '
#1340000000000
b1010010 .
1$
b100001100 '
#1345000000000
0$
b100001101 '
#1350000000000
b1010011 .
1$
b100001110 '
#1355000000000
0$
b100001111 '
#1360000000000
b1010100 .
1$
b100010000 '
#1365000000000
0$
b100010001 '
#1370000000000
b1010101 .
1$
b100010010 '
#1375000000000
0$
b100010011 '
#1380000000000
b1010110 .
1$
b100010100 '
#1385000000000
0$
b100010101 '
#1390000000000
b1010111 .
1$
b100010110 '
#1395000000000
0$
b100010111 '
#1400000000000
b1011000 .
1$
b100011000 '
#1405000000000
0$
b100011001 '
#1410000000000
b1011001 .
1$
b100011010 '
#1415000000000
0$
b100011011 '
#1420000000000
b1011010 .
1$
b100011100 '
#1425000000000
0$
b100011101 '
#1430000000000
b1011011 .
1$
b100011110 '
#1435000000000
0$
b100011111 '
#1440000000000
b1011100 .
1$
b100100000 '
#1445000000000
0$
b100100001 '
#1450000000000
b1011101 .
1$
b100100010 '
#1455000000000
0$
b100100011 '
#1460000000000
b1011110 .
1$
b100100100 '
#1465000000000
0$
b100100101 '
#1470000000000
b1011111 .
1$
b100100110 '
#1475000000000
0$
b100100111 '
#1480000000000
b1100000 .
1$
b100101000 '
#1485000000000
0$
b100101001 '
#1490000000000
b1100001 .
1$
b100101010 '
#1495000000000
0$
b100101011 '
#1500000000000
b1100010 .
1$
b100101100 '
#1505000000000
0$
b100101101 '
#1510000000000
b1100011 .
1$
b100101110 '
#1515000000000
0$
b100101111 '
#1520000000000
b1100100 .
1$
b100110000 '
#1525000000000
0$
b100110001 '
#1530000000000
1!
b1 .
1)
1$
b100110010 '
#1535000000000
0$
b100110011 '
#1540000000000
0!
b10 .
0)
1$
b100110100 '
#1545000000000
0$
b100110101 '
#1550000000000
b11 .
1$
b100110110 '
#1555000000000
0$
b100110111 '
#1560000000000
b100 .
1$
b100111000 '
#1565000000000
0$
b100111001 '
#1570000000000
b101 .
1$
b100111010 '
#1575000000000
0$
b100111011 '
#1580000000000
b110 .
1$
b100111100 '
#1585000000000
0$
b100111101 '
#1590000000000
b111 .
1$
b100111110 '
#1595000000000
0$
b100111111 '
#1600000000000
b1000 .
1$
b101000000 '
#1605000000000
0$
b101000001 '
#1610000000000
b1001 .
1$
b101000010 '
#1615000000000
0$
b101000011 '
#1620000000000
b1010 .
1$
b101000100 '
#1625000000000
0$
b101000101 '
#1630000000000
b1011 .
1$
b101000110 '
#1635000000000
0$
b101000111 '
#1640000000000
b1100 .
1$
b101001000 '
#1645000000000
0$
b101001001 '
#1650000000000
b1101 .
1$
b101001010 '
#1655000000000
0$
b101001011 '
#1660000000000
b1110 .
1$
b101001100 '
#1665000000000
0$
b101001101 '
#1670000000000
b1111 .
1$
b101001110 '
#1675000000000
0$
b101001111 '
#1680000000000
b10000 .
1$
b101010000 '
#1685000000000
0$
b101010001 '
#1690000000000
b10001 .
1$
b101010010 '
#1695000000000
0$
b101010011 '
#1700000000000
b10010 .
1$
b101010100 '
#1705000000000
0$
b101010101 '
#1710000000000
b10011 .
1$
b101010110 '
#1715000000000
0$
b101010111 '
#1720000000000
b10100 .
1$
b101011000 '
#1725000000000
0$
b101011001 '
#1730000000000
b10101 .
1$
b101011010 '
#1735000000000
0$
b101011011 '
#1740000000000
b10110 .
1$
b101011100 '
#1745000000000
0$
b101011101 '
#1750000000000
b10111 .
1$
b101011110 '
#1755000000000
0$
b101011111 '
#1760000000000
b11000 .
1$
b101100000 '
#1765000000000
0$
b101100001 '
#1770000000000
b11001 .
1$
b101100010 '
#1775000000000
0$
b101100011 '
#1780000000000
b11010 .
1$
b101100100 '
#1785000000000
0$
b101100101 '
#1790000000000
b11011 .
1$
b101100110 '
#1795000000000
0$
b101100111 '
#1800000000000
b11100 .
1$
b101101000 '
#1805000000000
0$
b101101001 '
#1810000000000
b11101 .
1$
b101101010 '
#1815000000000
0$
b101101011 '
#1820000000000
b11110 .
1$
b101101100 '
#1825000000000
0$
b101101101 '
#1830000000000
b11111 .
1$
b101101110 '
#1835000000000
0$
b101101111 '
#1840000000000
b100000 .
1$
b101110000 '
#1845000000000
0$
b101110001 '
#1850000000000
b100001 .
1$
b101110010 '
#1855000000000
0$
b101110011 '
#1860000000000
b100010 .
1$
b101110100 '
#1865000000000
0$
b101110101 '
#1870000000000
b100011 .
1$
b101110110 '
#1875000000000
0$
b101110111 '
#1880000000000
b100100 .
1$
b101111000 '
#1885000000000
0$
b101111001 '
#1890000000000
b100101 .
1$
b101111010 '
#1895000000000
0$
b101111011 '
#1900000000000
b100110 .
1$
b101111100 '
#1905000000000
0$
b101111101 '
#1910000000000
b100111 .
1$
b101111110 '
#1915000000000
0$
b101111111 '
#1920000000000
b101000 .
1$
b110000000 '
#1925000000000
0$
b110000001 '
#1930000000000
b101001 .
1$
b110000010 '
#1935000000000
0$
b110000011 '
#1940000000000
b101010 .
1$
b110000100 '
#1945000000000
0$
b110000101 '
#1950000000000
b101011 .
1$
b110000110 '
#1955000000000
0$
b110000111 '
#1960000000000
b101100 .
1$
b110001000 '
#1965000000000
0$
b110001001 '
#1970000000000
b101101 .
1$
b110001010 '
#1975000000000
0$
b110001011 '
#1980000000000
b101110 .
1$
b110001100 '
#1985000000000
0$
b110001101 '
#1990000000000
b101111 .
1$
b110001110 '
#1995000000000
0$
b110001111 '
#2000000000000
b110000 .
1$
b110010000 '
#2005000000000
0$
b110010001 '
#2010000000000
b110001 .
1$
b110010010 '
#2015000000000
0$
b110010011 '
#2020000000000
b110010 .
1$
b110010100 '
#2025000000000
0$
b110010101 '
#2030000000000
b110011 .
1$
b110010110 '
#2035000000000
0$
b110010111 '
#2040000000000
b110100 .
1$
b110011000 '
#2045000000000
0$
b110011001 '
#2050000000000
b110101 .
1$
b110011010 '
#2055000000000
0$
b110011011 '
#2060000000000
b110110 .
1$
b110011100 '
#2065000000000
0$
b110011101 '
#2070000000000
b110111 .
1$
b110011110 '
#2075000000000
0$
b110011111 '
#2080000000000
b111000 .
1$
b110100000 '
#2085000000000
0$
b110100001 '
#2090000000000
b111001 .
1$
b110100010 '
#2095000000000
0$
b110100011 '
#2100000000000
b111010 .
1$
b110100100 '
#2105000000000
0$
b110100101 '
#2110000000000
b111011 .
1$
b110100110 '
#2115000000000
0$
b110100111 '
#2120000000000
b111100 .
1$
b110101000 '
#2125000000000
0$
b110101001 '
#2130000000000
b111101 .
1$
b110101010 '
#2135000000000
0$
b110101011 '
#2140000000000
b111110 .
1$
b110101100 '
#2145000000000
0$
b110101101 '
#2150000000000
b111111 .
1$
b110101110 '
#2155000000000
0$
b110101111 '
#2160000000000
b1000000 .
1$
b110110000 '
#2165000000000
0$
b110110001 '
#2170000000000
b1000001 .
1$
b110110010 '
#2175000000000
0$
b110110011 '
#2180000000000
b1000010 .
1$
b110110100 '
#2185000000000
0$
b110110101 '
#2190000000000
b1000011 .
1$
b110110110 '
#2195000000000
0$
b110110111 '
#2200000000000
b1000100 .
1$
b110111000 '
#2205000000000
0$
b110111001 '
#2210000000000
b1000101 .
1$
b110111010 '
#2215000000000
0$
b110111011 '
#2220000000000
b1000110 .
1$
b110111100 '
#2225000000000
0$
b110111101 '
#2230000000000
b1000111 .
1$
b110111110 '
#2235000000000
0$
b110111111 '
#2240000000000
b1001000 .
1$
b111000000 '
#2245000000000
0$
b111000001 '
#2250000000000
b1001001 .
1$
b111000010 '
#2255000000000
0$
b111000011 '
#2260000000000
b1001010 .
1$
b111000100 '
#2265000000000
0$
b111000101 '
#2270000000000
b1001011 .
1$
b111000110 '
#2275000000000
0$
b111000111 '
#2280000000000
b1001100 .
1$
b111001000 '
#2285000000000
0$
b111001001 '
#2290000000000
b1001101 .
1$
b111001010 '
#2295000000000
0$
b111001011 '
#2300000000000
b1001110 .
1$
b111001100 '
#2305000000000
0$
b111001101 '
#2310000000000
b1001111 .
1$
b111001110 '
#2315000000000
0$
b111001111 '
#2320000000000
b1010000 .
1$
b111010000 '
#2325000000000
0$
b111010001 '
#2330000000000
b1010001 .
1$
b111010010 '
#2335000000000
0$
b111010011 '
#2340000000000
b1010010 .
1$
b111010100 '
#2345000000000
0$
b111010101 '
#2350000000000
b1010011 .
1$
b111010110 '
#2355000000000
0$
b111010111 '
#2360000000000
b1010100 .
1$
b111011000 '
#2365000000000
0$
b111011001 '
#2370000000000
b1010101 .
1$
b111011010 '
#2375000000000
0$
b111011011 '
#2380000000000
b1010110 .
1$
b111011100 '
#2385000000000
0$
b111011101 '
#2390000000000
b1010111 .
1$
b111011110 '
#2395000000000
0$
b111011111 '
#2400000000000
b1011000 .
1$
b111100000 '
#2405000000000
0$
b111100001 '
#2410000000000
b1011001 .
1$
b111100010 '
#2415000000000
0$
b111100011 '
#2420000000000
b1011010 .
1$
b111100100 '
#2425000000000
0$
b111100101 '
#2430000000000
b1011011 .
1$
b111100110 '
#2435000000000
0$
b111100111 '
#2440000000000
b1011100 .
1$
b111101000 '
#2445000000000
0$
b111101001 '
#2450000000000
b1011101 .
1$
b111101010 '
#2455000000000
0$
b111101011 '
#2460000000000
b1011110 .
1$
b111101100 '
#2465000000000
0$
b111101101 '
#2470000000000
b1011111 .
1$
b111101110 '
#2475000000000
0$
b111101111 '
#2480000000000
b1100000 .
1$
b111110000 '
#2485000000000
0$
b111110001 '
#2490000000000
b1100001 .
1$
b111110010 '
#2495000000000
0$
b111110011 '
#2500000000000
b1100010 .
1$
b111110100 '
#2505000000000
0$
b111110101 '
#2510000000000
b1100011 .
1$
b111110110 '
#2515000000000
0$
b111110111 '
#2520000000000
b1100100 .
1$
b111111000 '
#2525000000000
0$
b111111001 '
#2530000000000
1!
b1 .
1)
1$
b111111010 '
#2535000000000
0$
b111111011 '
#2540000000000
0!
b10 .
0)
1$
b111111100 '
#2545000000000
0$
b111111101 '
#2550000000000
b11 .
1$
b111111110 '
#2555000000000
0$
b111111111 '
#2560000000000
b100 .
1$
b1000000000 '
#2565000000000
0$
b1000000001 '
#2570000000000
b101 .
1$
b1000000010 '
#2575000000000
0$
b1000000011 '
#2580000000000
b110 .
1$
b1000000100 '
#2585000000000
0$
b1000000101 '
#2590000000000
b111 .
1$
b1000000110 '
#2595000000000
0$
b1000000111 '
#2600000000000
b1000 .
1$
b1000001000 '
#2605000000000
0$
b1000001001 '
#2610000000000
b1001 .
1$
b1000001010 '
#2615000000000
0$
b1000001011 '
#2620000000000
b1010 .
1$
b1000001100 '
#2625000000000
0$
b1000001101 '
#2630000000000
b1011 .
1$
b1000001110 '
#2635000000000
0$
b1000001111 '
#2640000000000
b1100 .
1$
b1000010000 '
#2645000000000
0$
b1000010001 '
#2650000000000
b1101 .
1$
b1000010010 '
#2655000000000
0$
b1000010011 '
#2660000000000
b1110 .
1$
b1000010100 '
#2665000000000
0$
b1000010101 '
#2670000000000
b1111 .
1$
b1000010110 '
#2675000000000
0$
b1000010111 '
#2680000000000
b10000 .
1$
b1000011000 '
#2685000000000
0$
b1000011001 '
#2690000000000
b10001 .
1$
b1000011010 '
#2695000000000
0$
b1000011011 '
#2700000000000
b10010 .
1$
b1000011100 '
#2705000000000
0$
b1000011101 '
#2710000000000
b10011 .
1$
b1000011110 '
#2715000000000
0$
b1000011111 '
#2720000000000
b10100 .
1$
b1000100000 '
#2725000000000
0$
b1000100001 '
#2730000000000
b10101 .
1$
b1000100010 '
#2735000000000
0$
b1000100011 '
#2740000000000
b10110 .
1$
b1000100100 '
#2745000000000
0$
b1000100101 '
#2750000000000
b10111 .
1$
b1000100110 '
#2755000000000
0$
b1000100111 '
#2760000000000
b11000 .
1$
b1000101000 '
#2765000000000
0$
b1000101001 '
#2770000000000
b11001 .
1$
b1000101010 '
#2775000000000
0$
b1000101011 '
#2780000000000
b11010 .
1$
b1000101100 '
#2785000000000
0$
b1000101101 '
#2790000000000
b11011 .
1$
b1000101110 '
#2795000000000
0$
b1000101111 '
#2800000000000
b11100 .
1$
b1000110000 '
#2805000000000
0$
b1000110001 '
#2810000000000
b11101 .
1$
b1000110010 '
#2815000000000
0$
b1000110011 '
#2820000000000
b11110 .
1$
b1000110100 '
#2825000000000
0$
b1000110101 '
#2830000000000
b11111 .
1$
b1000110110 '
#2835000000000
0$
b1000110111 '
#2840000000000
b100000 .
1$
b1000111000 '
#2845000000000
0$
b1000111001 '
#2850000000000
b100001 .
1$
b1000111010 '
#2855000000000
0$
b1000111011 '
#2860000000000
b100010 .
1$
b1000111100 '
#2865000000000
0$
b1000111101 '
#2870000000000
b100011 .
1$
b1000111110 '
#2875000000000
0$
b1000111111 '
#2880000000000
b100100 .
1$
b1001000000 '
#2885000000000
0$
b1001000001 '
#2890000000000
b100101 .
1$
b1001000010 '
#2895000000000
0$
b1001000011 '
#2900000000000
b100110 .
1$
b1001000100 '
#2905000000000
0$
b1001000101 '
#2910000000000
b100111 .
1$
b1001000110 '
#2915000000000
0$
b1001000111 '
#2920000000000
b101000 .
1$
b1001001000 '
#2925000000000
0$
b1001001001 '
#2930000000000
b101001 .
1$
b1001001010 '
#2935000000000
0$
b1001001011 '
#2940000000000
b101010 .
1$
b1001001100 '
#2945000000000
0$
b1001001101 '
#2950000000000
b101011 .
1$
b1001001110 '
#2955000000000
0$
b1001001111 '
#2960000000000
b101100 .
1$
b1001010000 '
#2965000000000
0$
b1001010001 '
#2970000000000
b101101 .
1$
b1001010010 '
#2975000000000
0$
b1001010011 '
#2980000000000
b101110 .
1$
b1001010100 '
#2985000000000
0$
b1001010101 '
#2990000000000
b101111 .
1$
b1001010110 '
#2995000000000
0$
b1001010111 '
#3000000000000
b110000 .
1$
b1001011000 '
#3005000000000
0$
b1001011001 '
