projeto02/projetoSD/parte3/controle_magnetron/magnetron_nvl2/magnetron_nvl3/sr_latch.v
module sr_latch (
    input wire S,
    input wire R,
    output reg Q
);

initial begin
    Q = 1'b0;
end

always @(S, R) begin
    if (S == 1'b1)
        Q = 1'b1;
    else if (R == 1'b1)
        Q = 1'b0;
end
    
endmodule

microwave_level1/microwave_level1/magnetron_level2/magnetron_level3/magnetron_logico.v
module magnetron_logico (
    input wire startn,
    input wire stopn,
    input wire clearn,
    input wire door_closed,
    input wire timer_done,
    output reg S,
    output reg R
);

initial begin
    S = 1'b0;
    R = 1'b0;
end

always @(startn, stopn, clearn, door_closed, timer_done) begin
    // Se stopn, clearn, ou door_closed é LOW ou timer_done é HIGH,
    // o valor do latch deve ser 0
    if (clearn == 1'b0 || stopn == 1'b0 || door_closed == 1'b0 || timer_done == 1'b1) begin
        S = 1'b0;
        R = 1'b1;
    end
    // Se o valor de startn for LOW, o valor do latch deve ser 1
    else if (startn == 1'b0) begin
        S = 1'b1;
        R = 1'b0;
    end
    // Em outras situações, o latch deve manter seu valor
    else begin
        S = 1'b0;
        R = 1'b0;
    end
end
    
endmodule

microwave_level1/microwave_level1/magnetron_level2/magnetron.v
`include "magnetron_level2/magnetron_level3/magnetron_logico.v"
`include "magnetron_level2/magnetron_level3/sr_latch.v"

module magnetron (
    input wire startn,
    input wire stopn,
    input wire clearn,
    input wire door_closed,
    input wire timer_done,
    output wire mag_on
);

    wire S, R;

    magnetron_logico mag_log(startn, stopn, clearn, door_closed, ~timer_done, S, R);
    sr_latch sr(S, R, mag_on);
    
endmodule

projeto02/projetoSD/parte3/controle_magnetron/magnetron_nvl2/magnetron_tb.v
`timescale 1ns/1ps
`include "magnetron.v"

module magnetron_tb ();

    reg startn;
    reg stopn;
    reg clearn;
    reg door_closed;
    reg timer_done;
    wire mag_on;

    magnetron dut (startn, stopn, clearn, door_closed, timer_done, mag_on);

    initial begin

        $dumpfile("magnetron.vcd");
        $dumpvars(0, magnetron_tb);

        startn = 1; stopn = 1; clearn = 1; door_closed = 1; timer_done = 0; #10;
        startn = 0; stopn = 1; clearn = 1; door_closed = 1; timer_done = 0; #10;
        startn = 1; stopn = 1; clearn = 1; door_closed = 1; timer_done = 0; #10;
        startn = 1; stopn = 0; clearn = 1; door_closed = 1; timer_done = 0; #10;
        startn = 1; stopn = 1; clearn = 1; door_closed = 1; timer_done = 0; #10;
        startn = 0; stopn = 1; clearn = 1; door_closed = 1; timer_done = 0; #10;
        startn = 1; stopn = 1; clearn = 1; door_closed = 1; timer_done = 0; #10;
        startn = 1; stopn = 1; clearn = 0; door_closed = 1; timer_done = 0; #10;
        startn = 1; stopn = 1; clearn = 1; door_closed = 1; timer_done = 0; #10;
        startn = 0; stopn = 1; clearn = 1; door_closed = 1; timer_done = 0; #10;
        startn = 1; stopn = 1; clearn = 1; door_closed = 1; timer_done = 0; #10;
        startn = 1; stopn = 1; clearn = 1; door_closed = 0; timer_done = 0; #10;
        startn = 1; stopn = 1; clearn = 1; door_closed = 1; timer_done = 0; #10;
        startn = 0; stopn = 1; clearn = 1; door_closed = 1; timer_done = 0; #10;
        startn = 1; stopn = 1; clearn = 1; door_closed = 1; timer_done = 0; #10;
        startn = 1; stopn = 1; clearn = 1; door_closed = 1; timer_done = 1; #10;
        startn = 1; stopn = 1; clearn = 1; door_closed = 1; timer_done = 0; #10;
        startn = 0; stopn = 1; clearn = 1; door_closed = 1; timer_done = 0; #10;
        startn = 1; stopn = 1; clearn = 1; door_closed = 1; timer_done = 0; #10;

    end
    
endmodule

microwave_level1/microwave_level1/magnetron_level2/magnetron.vcd
$date
	Thu May 12 01:53:31 2022
$end
$version
	Icarus Verilog
$end
$timescale
	1ps
$end
$scope module magnetron_tb $end
$var wire 1 ! mag_on $end
$var reg 1 " clearn $end
$var reg 1 # door_closed $end
$var reg 1 $ startn $end
$var reg 1 % stopn $end
$var reg 1 & timer_done $end
$scope module dut $end
$var wire 1 " clearn $end
$var wire 1 # door_closed $end
$var wire 1 $ startn $end
$var wire 1 % stopn $end
$var wire 1 & timer_done $end
$var wire 1 ! mag_on $end
$var wire 1 ' S $end
$var wire 1 ( R $end
$scope module mag_log $end
$var wire 1 " clearn $end
$var wire 1 # door_closed $end
$var wire 1 $ startn $end
$var wire 1 % stopn $end
$var wire 1 & timer_done $end
$var reg 1 ( R $end
$var reg 1 ' S $end
$upscope $end
$scope module sr $end
$var wire 1 ( R $end
$var wire 1 ' S $end
$var reg 1 ! Q $end
$upscope $end
$upscope $end
$upscope $end
$enddefinitions $end
#0
$dumpvars
0(
0'
0&
1%
1$
1#
1"
0!
$end
#10000
1!
1'
0$
#20000
0'
1$
#30000
0!
1(
0%
#40000
0(
1%
#50000
1!
1'
0$
#60000
0'
1$
#70000
0!
1(
0"
#80000
0(
1"
#90000
1!
1'
0$
#100000
0'
1$
#110000
0!
1(
0#
#120000
0(
1#
#130000
1!
1'
0$
#140000
0'
1$
#150000
0!
1(
1&
#160000
0(
0&
#170000
1!
1'
0$
#180000
0'
1$
