tiago-vitor-amorim/Nivel 1/Nivel 2/Entrada de timer e controle/Codificador/encoder.v
module encoder (output reg [3:0]B, output reg dv,
input wire [9:0]A, input wire en);
always @ (A, en)
begin
    //recebimento do timer
    if (A==1'b1 & en == 0)begin
         B = 4'b0000;//0
         dv = 1'b0;
         end
    else if (A==2'b10 & en == 0)begin
         B = 4'b0001; //1
         dv = 1'b0;
         end
    else if (A==3'b100 & en == 0)begin
         B = 4'b0010; //2
         dv = 1'b0;
         end
    else if (A==4'b1000 & en == 0)begin
         B = 4'b0011; //3
         dv = 1'b0;
         end
    else if (A==5'b10000 & en == 0)begin
         B = 4'b0100; //4
         dv = 1'b0;
         end
    else if (A==6'b100000 & en == 0)begin
         B = 4'b0101; //5
         dv = 1'b0;
         end
    else if (A==7'b1000000 & en == 0)begin
         B = 4'b0110; //6
         dv = 1'b0;
         end
    else if (A==8'b10000000 & en == 0)begin
         B = 4'b0111; //7
         dv = 1'b0;
         end
    else if (A==9'b100000000 & en == 0)begin
         B = 4'b1000; //8
         dv = 1'b0;
         end
    else if (A==10'b1000000000 & en == 0)begin
         B = 4'b1001; //9
         dv = 1'b0;
         end
    else begin
         B = 4'bXXXX;
         dv = 1'b1; 
         end
end   
endmodule

tiago-vitor-amorim/microondas_SD/Nivel 1/Nivel 2/Entrada de timer e controle/Codificador/encoder_tb.v
`timescale 1ns/1ps
`include "encoder.v"
module encoder_tb();
reg [9:0] A_tb; 
reg en_tb;
wire [3:0] B_tb;
wire dv_tb;
encoder DUT(.B(B_tb), .dv(dv_tb), .A(A_tb), .en(en_tb));
initial 
    begin
        $dumpfile("encoder.vcd");
        $dumpvars(0, encoder_tb);
        en_tb = 1'b0; A_tb = 1'b1; 
        #10 en_tb = 1'b0; A_tb = 2'b10;
        #10 en_tb = 1'b0; A_tb = 3'b100;
        #10 en_tb = 1'b0; A_tb = 4'b1000;
        #10 en_tb = 1'b0; A_tb = 5'b10000;
        #10 en_tb = 1'b0; A_tb = 6'b100000;
        #10 en_tb = 1'b0; A_tb = 7'b1000000;
        #10 en_tb = 1'b0; A_tb = 8'b10000000;
        #10 en_tb = 1'b0; A_tb = 9'b100000000;
        #10 en_tb = 1'b0; A_tb = 10'b1000000000;
        #10 en_tb = 1'b1; A_tb = 1'b1;
        #10 en_tb = 1'b1; A_tb = 2'b10;
        #10 en_tb = 1'b1; A_tb = 3'b100;
        #10 en_tb = 1'b1; A_tb = 4'b1000;
        #10 en_tb = 1'b1; A_tb = 5'b10000;
        #10 en_tb = 1'b1; A_tb = 6'b100000;
        #10 en_tb = 1'b1; A_tb = 7'b1000000;
        #10 en_tb = 1'b1; A_tb = 8'b10000000;
        #10 en_tb = 1'b1; A_tb = 9'b100000000;
        #10 en_tb = 1'b0; A_tb = 10'b1000000000;
    end
    
endmodule

tiago-vitor-amorim/microondas_SD/Nivel 1/Nivel 2/Entrada de timer e controle/Codificador/encoder.vcd
$date
	Fri May 06 18:59:36 2022
$end
$version
	Icarus Verilog
$end
$timescale
	1ps
$end
$scope module encoder_tb $end
$var wire 1 ! dv_tb $end
$var wire 4 " B_tb [3:0] $end
$var reg 10 # A_tb [9:0] $end
$var reg 1 $ en_tb $end
$scope module DUT $end
$var wire 10 % A [9:0] $end
$var wire 1 $ en $end
$var reg 4 & B [3:0] $end
$var reg 1 ! dv $end
$upscope $end
$upscope $end
$enddefinitions $end
#0
$dumpvars
b0 &
b1 %
0$
b1 #
b0 "
0!
$end
#10000
b1 "
b1 &
b10 #
b10 %
#20000
b10 "
b10 &
b100 #
b100 %
#30000
b11 "
b11 &
b1000 #
b1000 %
#40000
b100 "
b100 &
b10000 #
b10000 %
#50000
b101 "
b101 &
b100000 #
b100000 %
#60000
b110 "
b110 &
b1000000 #
b1000000 %
#70000
b111 "
b111 &
b10000000 #
b10000000 %
#80000
b1000 "
b1000 &
b100000000 #
b100000000 %
#90000
b1001 "
b1001 &
b1000000000 #
b1000000000 %
#100000
1!
b1111 "
b1111 &
b1 #
b1 %
1$
#110000
b10 #
b10 %
#120000
b100 #
b100 %
#130000
b1000 #
b1000 %
#140000
b10000 #
b10000 %
#150000
b100000 #
b100000 %
#160000
b1000000 #
b1000000 %
#170000
b10000000 #
b10000000 %
#180000
b100000000 #
b100000000 %
#190000
0!
b1001 "
b1001 &
b1000000000 #
b1000000000 %
0$
