tiago-vitor-amorim/microondas_SD/Nivel 1/Nivel 2/controle de magnetron/Nivel 3/sr_latch/sr_latch.v
module sr_latch (
    input wire set, reset,
    output reg mag_on
);

//||=or && = and
    always @(set || reset) begin
        if(reset && !set) begin
            mag_on <= 1'b0;
        end
        else if(set && !reset) begin
            mag_on <= 1'b1;
        end
        else if(!set && !reset) begin
            mag_on <= mag_on;
        end
    end
    
endmodule

tiago-vitor-amorim/Nivel 1/Nivel 2/controle de magnetron/Nivel 3/LogicQuest/logicQuest.v
module logicQuest (
    input wire startn, stopn, clearn, door_closed, timer_done, 
    output reg S, R
    );
    
    //||=or && = and
    always @(startn, stopn, clearn, door_closed, timer_done) begin
        if(!clearn || !stopn || timer_done || !door_closed) begin
                S   <= 1'b0;
                R <= 1'b1;
                //mag_on = 0
        end
        else if(!startn && door_closed) begin
                S   <= 1'b1;
                R <= 1'b0;
                //mag_on = 1
        end
        else begin
            S   <= 1'b0;
            R <= 1'b0;
        end
    end

endmodule

tiago-vitor-amorim/microondas_SD/Nivel 1/Nivel 2/controle de magnetron/magn.v
`include "Nivel 3/Logicquest/logicQuest.v"
`include "Nivel 3/sr_latch/sr_latch.v"
module magn (
    input wire startn, stopn, clearn, door_closed, timer_done,
    output wire mag_on
);
    wire set, reset;
  	
    logicQuest U1(.startn(startn), .stopn(stopn), .clearn(clearn), 
                  .door_closed(door_closed), .timer_done(timer_done), .S(set), .R(reset));

    sr_latch U2(.set(set), .reset(reset), .mag_on(mag_on));

endmodule

tiago-vitor-amorim/microondas_SD/Nivel 1/Nivel 2/controle de magnetron/magn_tb.v
`timescale 1ns/1ps
`include "magn.v"
`include "logicQuest.v"
`include "sr_latch.v"

module magn_tb();

    reg startn_tb, stopn_tb, clearn_tb, door_closed_tb, timer_done_tb;
    wire mag_on_tb;

    magn DUT(
    .startn(startn_tb), .stopn(stopn_tb), .clearn(clearn_tb), 
    .door_closed(door_closed_tb), .timer_done(timer_done_tb), 
    .mag_on(mag_on_tb));

integer i;

    initial begin
        
        $dumpfile("magn_tb.vcd");
        $dumpvars(0,magn_tb);
        for(i=0 ; i<3000; i++)begin
        #10startn_tb = (i%2);
            stopn_tb = $urandom%2;
            clearn_tb = $urandom%2;
            door_closed_tb =$urandom%2;
            timer_done_tb = $urandom%2;
        end
    end
endmodule

tiago-vitor-amorim/Nivel 1/Nivel 2/controle de magnetron/magn_tb.vcd
$date
	Thu May 12 19:33:41 2022
$end
$version
	Icarus Verilog
$end
$timescale
	1ps
$end
$scope module magn_tb $end
$var wire 1 ! mag_on_tb $end
$var reg 1 " clearn_tb $end
$var reg 1 # door_closed_tb $end
$var reg 1 $ startn_tb $end
$var reg 1 % stopn_tb $end
$var reg 1 & timer_done_tb $end
$var integer 32 ' i [31:0] $end
$scope module DUT $end
$var wire 1 " clearn $end
$var wire 1 # door_closed $end
$var wire 1 $ startn $end
$var wire 1 % stopn $end
$var wire 1 & timer_done $end
$var wire 1 ( set $end
$var wire 1 ) reset $end
$var wire 1 ! mag_on $end
$scope module U1 $end
$var wire 1 " clearn $end
$var wire 1 # door_closed $end
$var wire 1 $ startn $end
$var wire 1 % stopn $end
$var wire 1 & timer_done $end
$var reg 1 ) R $end
$var reg 1 ( S $end
$upscope $end
$scope module U2 $end
$var wire 1 ) reset $end
$var wire 1 ( set $end
$var reg 1 ! mag_on $end
$upscope $end
$upscope $end
$upscope $end
$enddefinitions $end
#0
$dumpvars
x)
x(
b0 '
x&
x%
x$
x#
x"
x!
$end
#10000
0!
1)
0(
b1 '
1&
1#
1"
0%
0$
#20000
0)
b10 '
0&
1%
1$
#30000
1)
b11 '
1&
0#
0$
#40000
b100 '
0&
1#
0"
1$
#50000
b101 '
1&
0$
#60000
b110 '
0&
0#
1"
0%
1$
#70000
b111 '
1&
0$
#80000
0)
b1000 '
0&
1#
1%
1$
#90000
1)
b1001 '
1&
0#
0"
0%
0$
#100000
b1010 '
1#
1"
1$
#110000
b1011 '
0&
0#
1%
0$
#120000
0)
b1100 '
1#
1$
#130000
1)
b1101 '
0#
0"
0%
0$
#140000
b1110 '
1&
1%
1$
#150000
b1111 '
0&
0$
#160000
b10000 '
1&
1#
0%
1$
#170000
0)
1(
b10001 '
0&
1"
1%
0$
#180000
1)
0(
b10010 '
1&
0%
1$
#190000
b10011 '
0"
0$
#200000
b10100 '
0&
1"
1$
#210000
0)
1(
b10101 '
1%
0$
#220000
1)
0(
b10110 '
0#
1$
#230000
b10111 '
1&
1#
0"
0%
0$
#240000
b11000 '
1$
#250000
0)
1(
b11001 '
0&
1"
1%
0$
#260000
0(
b11010 '
1$
#270000
1)
b11011 '
0#
0"
0%
0$
#280000
b11100 '
1&
1#
1$
#290000
0)
1(
b11101 '
0&
1"
1%
0$
#300000
1)
0(
b11110 '
0#
1$
#310000
b11111 '
1&
0$
#320000
0)
b100000 '
0&
1#
1$
#330000
1)
b100001 '
0"
0%
0$
#340000
b100010 '
1&
1$
#350000
b100011 '
0&
0$
#360000
b100100 '
1$
#370000
b100101 '
1&
0#
1"
0$
#380000
b100110 '
1#
1%
1$
#390000
b100111 '
0#
0"
0%
0$
#400000
b101000 '
1#
1$
#410000
b101001 '
0#
0$
#420000
b101010 '
0&
1%
1$
#430000
b101011 '
1"
0$
#440000
b101100 '
0%
1$
#450000
b101101 '
0"
1%
0$
#460000
b101110 '
1&
1#
1$
#470000
b101111 '
0&
0#
0%
0$
#480000
b110000 '
1%
1$
#490000
b110001 '
1&
1#
1"
0%
0$
#500000
b110010 '
1$
#510000
b110011 '
0"
0$
#520000
0)
b110100 '
0&
1"
1%
1$
#530000
1)
b110101 '
0#
0$
#540000
b110110 '
1&
1#
0"
0%
1$
#550000
b110111 '
0&
0$
#560000
b111000 '
0#
1"
1$
#570000
b111001 '
1&
0"
1%
0$
#580000
b111010 '
0&
1"
1$
#590000
b111011 '
0%
0$
#600000
b111100 '
0"
1%
1$
#610000
b111101 '
1"
0%
0$
#620000
b111110 '
1#
1$
#630000
b111111 '
1&
1%
0$
#640000
b1000000 '
0%
1$
#650000
b1000001 '
0&
0"
0$
#660000
b1000010 '
1"
1$
#670000
b1000011 '
0#
0$
#680000
b1000100 '
1&
1#
0"
1%
1$
#690000
b1000101 '
0#
1"
0%
0$
#700000
b1000110 '
0&
1#
0"
1$
#710000
b1000111 '
1&
0$
#720000
0)
b1001000 '
0&
1"
1%
1$
#730000
1!
1(
b1001001 '
0$
#740000
1)
0(
b1001010 '
0#
0"
0%
1$
#750000
b1001011 '
1&
1#
1"
0$
#760000
b1001100 '
1%
1$
#770000
b1001101 '
0%
0$
#780000
b1001110 '
1%
1$
#790000
b1001111 '
0#
0"
0$
#800000
b1010000 '
0&
1$
#810000
b1010001 '
1"
0%
0$
#820000
b1010010 '
0"
1$
#830000
b1010011 '
1&
1%
0$
#840000
b1010100 '
0&
0%
1$
#850000
b1010101 '
1&
1#
1"
1%
0$
#860000
b1010110 '
0"
1$
#870000
b1010111 '
0&
0$
#880000
b1011000 '
1"
0%
1$
#890000
b1011001 '
1&
0#
0"
1%
0$
#900000
b1011010 '
0&
0%
1$
#910000
b1011011 '
1&
1#
1"
1%
0$
#920000
b1011100 '
0%
1$
#930000
b1011101 '
1%
0$
#940000
b1011110 '
0#
0%
1$
#950000
b1011111 '
0&
1#
0"
0$
#960000
b1100000 '
0#
1$
#970000
b1100001 '
1%
0$
#980000
b1100010 '
1&
0%
1$
#990000
b1100011 '
0&
1"
0$
#1000000
b1100100 '
1&
1#
0"
1%
1$
#1010000
b1100101 '
0#
1"
0%
0$
#1020000
b1100110 '
0&
0"
1$
#1030000
b1100111 '
1#
1%
0$
#1040000
b1101000 '
1&
0#
1"
1$
#1050000
b1101001 '
1#
0%
0$
#1060000
b1101010 '
0&
1$
#1070000
b1101011 '
0$
#1080000
b1101100 '
1$
#1090000
b1101101 '
0#
0$
#1100000
b1101110 '
1%
1$
#1110000
b1101111 '
1&
0"
0$
#1120000
b1110000 '
0&
1#
1$
#1130000
b1110001 '
1&
0#
1"
0$
#1140000
b1110010 '
1$
#1150000
b1110011 '
0&
0$
#1160000
b1110100 '
1&
0"
1$
#1170000
b1110101 '
1#
0%
0$
#1180000
b1110110 '
0#
1"
1$
#1190000
0)
1(
b1110111 '
0&
1#
1%
0$
#1200000
1)
0(
b1111000 '
1&
0#
0%
1$
#1210000
b1111001 '
0&
1#
0$
#1220000
b1111010 '
1&
1$
#1230000
b1111011 '
0&
0"
0$
#1240000
b1111100 '
1&
1"
1$
#1250000
b1111101 '
0&
0$
#1260000
b1111110 '
1&
0"
1$
#1270000
b1111111 '
0&
0#
1%
0$
#1280000
b10000000 '
1&
1#
1"
1$
#1290000
b10000001 '
0%
0$
#1300000
b10000010 '
1%
1$
#1310000
b10000011 '
0&
0#
0%
0$
#1320000
b10000100 '
1&
1#
1$
#1330000
b10000101 '
1%
0$
#1340000
b10000110 '
0&
0#
1$
#1350000
b10000111 '
0%
0$
#1360000
b10001000 '
1#
1$
#1370000
b10001001 '
1&
0"
0$
#1380000
b10001010 '
0#
1"
1$
#1390000
b10001011 '
0"
0$
#1400000
b10001100 '
1"
1%
1$
#1410000
b10001101 '
0%
0$
#1420000
b10001110 '
0&
0"
1%
1$
#1430000
b10001111 '
1#
1"
0%
0$
#1440000
b10010000 '
1&
0#
1$
#1450000
b10010001 '
0&
1#
0$
#1460000
b10010010 '
0#
1%
1$
#1470000
b10010011 '
1&
1#
0"
0%
0$
#1480000
0)
b10010100 '
0&
1"
1%
1$
#1490000
0!
1)
b10010101 '
0#
0"
0%
0$
#1500000
b10010110 '
1&
1#
1$
#1510000
b10010111 '
1"
1%
0$
#1520000
b10011000 '
0&
0#
0"
1$
#1530000
b10011001 '
1&
0%
0$
#1540000
b10011010 '
0&
1#
1%
1$
#1550000
0)
1(
b10011011 '
1"
0$
#1560000
1)
0(
b10011100 '
1&
0"
0%
1$
#1570000
b10011101 '
0&
0#
1"
0$
#1580000
b10011110 '
0"
1$
#1590000
b10011111 '
1&
1%
0$
#1600000
b10100000 '
1#
0%
1$
#1610000
b10100001 '
0#
1%
0$
#1620000
0)
b10100010 '
0&
1#
1"
1$
#1630000
1)
b10100011 '
1&
0$
#1640000
b10100100 '
0&
0#
0%
1$
#1650000
b10100101 '
1&
0"
1%
0$
#1660000
b10100110 '
0&
0%
1$
#1670000
b10100111 '
1&
1#
0$
#1680000
b10101000 '
1$
#1690000
b10101001 '
1"
1%
0$
#1700000
b10101010 '
0&
0"
1$
#1710000
b10101011 '
1&
0%
0$
#1720000
b10101100 '
1"
1$
#1730000
b10101101 '
0&
0#
0"
0$
#1740000
0)
b10101110 '
1#
1"
1%
1$
#1750000
1)
b10101111 '
0#
0"
0$
#1760000
b10110000 '
0%
1$
#1770000
b10110001 '
1&
1%
0$
#1780000
b10110010 '
1#
1"
1$
#1790000
b10110011 '
0&
0#
0"
0%
0$
#1800000
b10110100 '
1"
1%
1$
#1810000
b10110101 '
1&
1#
0$
#1820000
b10110110 '
0&
0#
0"
1$
#1830000
b10110111 '
1#
0$
#1840000
b10111000 '
0#
0%
1$
#1850000
b10111001 '
1&
1#
1%
0$
#1860000
b10111010 '
0&
1"
0%
1$
#1870000
b10111011 '
1&
0"
1%
0$
#1880000
b10111100 '
0%
1$
#1890000
b10111101 '
0&
0#
0$
#1900000
0)
b10111110 '
1#
1"
1%
1$
#1910000
1)
b10111111 '
1&
0%
0$
#1920000
b11000000 '
0#
0"
1%
1$
#1930000
b11000001 '
0$
#1940000
b11000010 '
1"
0%
1$
#1950000
b11000011 '
0&
0"
1%
0$
#1960000
b11000100 '
1#
0%
1$
#1970000
b11000101 '
0#
1%
0$
#1980000
b11000110 '
1&
1$
#1990000
b11000111 '
1#
1"
0%
0$
#2000000
b11001000 '
0#
1%
1$
#2010000
b11001001 '
0"
0$
#2020000
b11001010 '
1#
1"
0%
1$
#2030000
b11001011 '
0#
1%
0$
#2040000
b11001100 '
0%
1$
#2050000
b11001101 '
0&
0"
1%
0$
#2060000
b11001110 '
1#
1"
0%
1$
#2070000
b11001111 '
1&
0$
#2080000
b11010000 '
0&
0#
1%
1$
#2090000
b11010001 '
1#
0"
0%
0$
#2100000
b11010010 '
1&
0#
1"
1$
#2110000
b11010011 '
0&
1#
0"
0$
#2120000
b11010100 '
1&
0#
1$
#2130000
b11010101 '
0&
1#
1"
0$
#2140000
b11010110 '
1&
0#
1$
#2150000
0)
1(
b11010111 '
0&
1#
1%
0$
#2160000
1)
0(
b11011000 '
1&
0#
0"
1$
#2170000
b11011001 '
1"
0$
#2180000
b11011010 '
1#
1$
#2190000
b11011011 '
0&
0"
0$
#2200000
b11011100 '
0%
1$
#2210000
b11011101 '
1%
0$
#2220000
b11011110 '
1&
0#
0%
1$
#2230000
b11011111 '
0&
1#
0$
#2240000
b11100000 '
1&
0#
1%
1$
#2250000
b11100001 '
0$
#2260000
b11100010 '
1#
1$
#2270000
b11100011 '
0#
1"
0$
#2280000
b11100100 '
1#
0"
0%
1$
#2290000
b11100101 '
0&
1"
0$
#2300000
0)
b11100110 '
1%
1$
#2310000
1)
b11100111 '
0"
0$
#2320000
b11101000 '
0#
0%
1$
#2330000
b11101001 '
0$
#2340000
0)
b11101010 '
1#
1"
1%
1$
#2350000
1)
b11101011 '
1&
0"
0%
0$
#2360000
b11101100 '
1"
1$
#2370000
b11101101 '
0"
0$
#2380000
b11101110 '
0&
0#
1$
#2390000
b11101111 '
1&
1#
1%
0$
#2400000
b11110000 '
0#
1"
0%
1$
#2410000
b11110001 '
1#
0"
1%
0$
#2420000
b11110010 '
0#
1"
1$
#2430000
b11110011 '
0&
0%
0$
#2440000
b11110100 '
1#
0"
1$
#2450000
b11110101 '
1&
0#
1%
0$
#2460000
0)
b11110110 '
0&
1#
1"
1$
#2470000
1!
1(
b11110111 '
0$
#2480000
1)
0(
b11111000 '
1&
0%
1$
#2490000
b11111001 '
0&
0$
#2500000
b11111010 '
0#
1$
#2510000
b11111011 '
1%
0$
#2520000
b11111100 '
0"
1$
#2530000
b11111101 '
1&
1#
1"
0$
#2540000
b11111110 '
0#
1$
#2550000
b11111111 '
0%
0$
#2560000
b100000000 '
1$
#2570000
b100000001 '
0$
#2580000
b100000010 '
0"
1$
#2590000
b100000011 '
1#
0$
#2600000
0)
b100000100 '
0&
1"
1%
1$
#2610000
0!
1)
b100000101 '
1&
0#
0$
#2620000
b100000110 '
1#
0%
1$
#2630000
b100000111 '
0#
1%
0$
#2640000
b100001000 '
1#
0%
1$
#2650000
b100001001 '
0"
1%
0$
#2660000
b100001010 '
0&
0#
1"
1$
#2670000
b100001011 '
1#
0%
0$
#2680000
b100001100 '
1&
0"
1$
#2690000
b100001101 '
0#
1%
0$
#2700000
b100001110 '
0&
0%
1$
#2710000
b100001111 '
1&
1#
0$
#2720000
b100010000 '
0&
0#
1$
#2730000
b100010001 '
1&
1#
1"
0$
#2740000
b100010010 '
0&
0#
1%
1$
#2750000
b100010011 '
1&
1#
0"
0%
0$
#2760000
0)
b100010100 '
0&
1"
1%
1$
#2770000
1)
b100010101 '
0"
0%
0$
#2780000
b100010110 '
1$
#2790000
b100010111 '
1&
1"
1%
0$
#2800000
b100011000 '
0#
0"
0%
1$
#2810000
b100011001 '
0&
1"
1%
0$
#2820000
b100011010 '
1&
0"
0%
1$
#2830000
b100011011 '
0&
1"
1%
0$
#2840000
b100011100 '
1&
0%
1$
#2850000
b100011101 '
1#
0$
#2860000
b100011110 '
0"
1%
1$
#2870000
b100011111 '
0&
0%
0$
#2880000
b100100000 '
1$
#2890000
b100100001 '
1&
0#
1"
0$
#2900000
b100100010 '
1%
1$
#2910000
b100100011 '
1#
0%
0$
#2920000
b100100100 '
0&
0#
0"
1$
#2930000
b100100101 '
1&
0$
#2940000
b100100110 '
1#
1"
1%
1$
#2950000
b100100111 '
0&
0#
0$
#2960000
0)
b100101000 '
1#
1$
#2970000
1)
b100101001 '
1&
0#
0$
#2980000
b100101010 '
1#
0%
1$
#2990000
b100101011 '
0#
0$
#3000000
b100101100 '
0&
0"
1%
1$
#3010000
b100101101 '
0$
#3020000
b100101110 '
1#
0%
1$
#3030000
b100101111 '
0$
#3040000
b100110000 '
1&
0#
1"
1%
1$
#3050000
b100110001 '
0&
0"
0%
0$
#3060000
b100110010 '
1&
1#
1"
1%
1$
#3070000
b100110011 '
0&
0"
0%
0$
#3080000
0)
b100110100 '
1"
1%
1$
#3090000
1)
b100110101 '
1&
0#
0$
#3100000
0)
b100110110 '
0&
1#
1$
#3110000
1)
b100110111 '
1&
0"
0%
0$
#3120000
b100111000 '
0&
1%
1$
#3130000
b100111001 '
1"
0%
0$
#3140000
b100111010 '
1&
0#
1$
#3150000
b100111011 '
0&
1#
0$
#3160000
0)
b100111100 '
1%
1$
#3170000
1)
b100111101 '
0"
0%
0$
#3180000
b100111110 '
0#
1"
1$
#3190000
b100111111 '
1&
0"
1%
0$
#3200000
b101000000 '
0&
1$
#3210000
b101000001 '
1&
1"
0$
#3220000
b101000010 '
0&
1#
0"
1$
#3230000
0)
1(
b101000011 '
1"
0$
#3240000
1)
0(
b101000100 '
1&
0#
1$
#3250000
b101000101 '
0&
0%
0$
#3260000
b101000110 '
1&
1#
1%
1$
#3270000
b101000111 '
0"
0%
0$
#3280000
b101001000 '
0#
1%
1$
#3290000
b101001001 '
1#
0$
#3300000
b101001010 '
0#
1"
1$
#3310000
b101001011 '
0"
0%
0$
#3320000
b101001100 '
0&
1#
1$
#3330000
b101001101 '
0#
1%
0$
#3340000
b101001110 '
1$
#3350000
b101001111 '
1&
1"
0$
#3360000
b101010000 '
0&
0"
1$
#3370000
b101010001 '
1&
1#
0$
#3380000
b101010010 '
0#
1"
0%
1$
#3390000
b101010011 '
0$
#3400000
b101010100 '
1#
0"
1%
1$
#3410000
b101010101 '
0#
1"
0%
0$
#3420000
b101010110 '
0&
1#
0"
1$
#3430000
b101010111 '
0$
#3440000
b101011000 '
0#
1$
#3450000
b101011001 '
1&
1#
0$
#3460000
b101011010 '
0#
1%
1$
#3470000
b101011011 '
1#
1"
0%
0$
#3480000
b101011100 '
0&
0#
1%
1$
#3490000
b101011101 '
1&
0"
0%
0$
#3500000
0)
b101011110 '
0&
1#
1"
1%
1$
#3510000
1)
b101011111 '
1&
0"
0%
0$
#3520000
b101100000 '
0&
1%
1$
#3530000
b101100001 '
0#
0$
#3540000
b101100010 '
0%
1$
#3550000
b101100011 '
1&
0$
#3560000
b101100100 '
1#
1"
1%
1$
#3570000
b101100101 '
0"
0%
0$
#3580000
b101100110 '
0#
1"
1$
#3590000
b101100111 '
0&
0"
0$
#3600000
0)
b101101000 '
1#
1"
1%
1$
#3610000
1)
b101101001 '
1&
0#
0$
#3620000
b101101010 '
0"
0%
1$
#3630000
b101101011 '
1%
0$
#3640000
b101101100 '
1#
1"
1$
#3650000
b101101101 '
0#
0"
0%
0$
#3660000
b101101110 '
0&
1#
1%
1$
#3670000
0)
1(
b101101111 '
1"
0$
#3680000
1)
0(
b101110000 '
0#
0"
1$
#3690000
b101110001 '
1&
1"
0%
0$
#3700000
b101110010 '
0&
0"
1%
1$
#3710000
b101110011 '
1&
1"
0$
#3720000
b101110100 '
0&
1#
0%
1$
#3730000
0)
1(
b101110101 '
1%
0$
#3740000
1)
0(
b101110110 '
1&
1$
#3750000
b101110111 '
0%
0$
#3760000
b101111000 '
0#
1%
1$
#3770000
b101111001 '
0$
#3780000
b101111010 '
0&
1#
0%
1$
#3790000
b101111011 '
0#
0"
1%
0$
#3800000
b101111100 '
1&
1"
0%
1$
#3810000
b101111101 '
0&
1#
0$
#3820000
b101111110 '
1&
0#
1$
#3830000
0)
1(
b101111111 '
0&
1#
1%
0$
#3840000
1)
0(
b110000000 '
1&
0#
1$
#3850000
b110000001 '
0&
1#
0%
0$
#3860000
b110000010 '
0#
1%
1$
#3870000
b110000011 '
0"
0$
#3880000
b110000100 '
1&
1#
1"
0%
1$
#3890000
b110000101 '
0&
0"
0$
#3900000
b110000110 '
1$
#3910000
b110000111 '
0#
1"
0$
#3920000
b110001000 '
1&
1$
#3930000
0)
1(
b110001001 '
0&
1#
1%
0$
#3940000
1)
0(
b110001010 '
0%
1$
#3950000
b110001011 '
1&
0#
0"
1%
0$
#3960000
b110001100 '
1#
1"
0%
1$
#3970000
0)
1(
b110001101 '
0&
1%
0$
#3980000
1)
0(
b110001110 '
0"
1$
#3990000
b110001111 '
1&
0$
#4000000
b110010000 '
0&
1$
#4010000
b110010001 '
0#
0$
#4020000
0)
b110010010 '
1#
1"
1$
#4030000
1)
b110010011 '
1&
0#
0"
0$
#4040000
b110010100 '
1$
#4050000
b110010101 '
0&
1"
0%
0$
#4060000
b110010110 '
1&
1#
1%
1$
#4070000
b110010111 '
0&
0"
0$
#4080000
b110011000 '
0#
1"
0%
1$
#4090000
b110011001 '
1%
0$
#4100000
b110011010 '
1&
0%
1$
#4110000
b110011011 '
1#
0"
1%
0$
#4120000
b110011100 '
1"
0%
1$
#4130000
b110011101 '
0"
0$
#4140000
b110011110 '
0#
1"
1$
#4150000
0)
1(
b110011111 '
0&
1#
1%
0$
#4160000
1)
0(
b110100000 '
1&
0"
0%
1$
#4170000
0)
1(
b110100001 '
0&
1"
1%
0$
#4180000
1)
0(
b110100010 '
1&
0#
0"
0%
1$
#4190000
b110100011 '
0&
1#
0$
#4200000
b110100100 '
1"
1$
#4210000
b110100101 '
0"
1%
0$
#4220000
b110100110 '
0#
1$
#4230000
b110100111 '
1&
0%
0$
#4240000
b110101000 '
0&
1"
1$
#4250000
b110101001 '
1&
0"
1%
0$
#4260000
b110101010 '
1$
#4270000
b110101011 '
0%
0$
#4280000
b110101100 '
0&
1$
#4290000
b110101101 '
1#
1"
0$
#4300000
b110101110 '
0#
1%
1$
#4310000
b110101111 '
0"
0%
0$
#4320000
b110110000 '
1#
1"
1$
#4330000
b110110001 '
1&
0$
#4340000
b110110010 '
0&
0#
0"
1%
1$
#4350000
b110110011 '
1&
1"
0%
0$
#4360000
b110110100 '
1#
1$
#4370000
b110110101 '
0#
1%
0$
#4380000
b110110110 '
1#
0%
1$
#4390000
b110110111 '
0"
0$
#4400000
b110111000 '
0&
1"
1$
#4410000
b110111001 '
0$
#4420000
b110111010 '
1&
0#
1$
#4430000
b110111011 '
0&
1#
0$
#4440000
b110111100 '
1&
1%
1$
#4450000
0)
1(
b110111101 '
0&
0$
#4460000
1)
0(
b110111110 '
1&
1$
#4470000
b110111111 '
0"
0$
#4480000
b111000000 '
0&
0#
1"
1$
#4490000
b111000001 '
1&
0$
#4500000
b111000010 '
0&
1#
0"
1$
#4510000
b111000011 '
0$
#4520000
b111000100 '
0#
0%
1$
#4530000
b111000101 '
1&
0$
#4540000
b111000110 '
0&
1#
1%
1$
#4550000
b111000111 '
1&
1"
0%
0$
#4560000
b111001000 '
0&
0#
0"
1%
1$
#4570000
0)
1(
b111001001 '
1#
1"
0$
#4580000
1)
0(
b111001010 '
0"
0%
1$
#4590000
b111001011 '
1&
1%
0$
#4600000
b111001100 '
0&
1"
0%
1$
#4610000
b111001101 '
0#
1%
0$
#4620000
b111001110 '
1#
0"
0%
1$
#4630000
b111001111 '
0#
0$
#4640000
b111010000 '
1&
1#
1$
#4650000
b111010001 '
1%
0$
#4660000
b111010010 '
0&
0%
1$
#4670000
b111010011 '
0#
0$
#4680000
b111010100 '
1%
1$
#4690000
b111010101 '
1&
1#
1"
0$
#4700000
b111010110 '
1$
#4710000
b111010111 '
0&
0"
0$
#4720000
b111011000 '
1&
1"
0%
1$
#4730000
b111011001 '
0&
0"
0$
#4740000
b111011010 '
0#
1"
1$
#4750000
b111011011 '
1&
0"
0$
#4760000
b111011100 '
0&
1"
1%
1$
#4770000
b111011101 '
1&
1#
0"
0$
#4780000
b111011110 '
0&
1$
#4790000
b111011111 '
0#
0%
0$
#4800000
b111100000 '
1&
1#
1"
1%
1$
#4810000
b111100001 '
0#
0"
0$
#4820000
b111100010 '
0&
1"
1$
#4830000
b111100011 '
0"
0%
0$
#4840000
b111100100 '
1&
1"
1%
1$
#4850000
b111100101 '
0&
1#
0"
0%
0$
#4860000
b111100110 '
0#
1$
#4870000
b111100111 '
1&
1#
0$
#4880000
b111101000 '
0#
1"
1%
1$
#4890000
b111101001 '
0&
0"
0%
0$
#4900000
b111101010 '
1#
1%
1$
#4910000
b111101011 '
1"
0%
0$
#4920000
b111101100 '
1$
#4930000
b111101101 '
0"
1%
0$
#4940000
b111101110 '
1&
0#
1"
0%
1$
#4950000
b111101111 '
0&
1#
0"
0$
#4960000
b111110000 '
0#
1%
1$
#4970000
b111110001 '
1&
0%
0$
#4980000
b111110010 '
0&
1%
1$
#4990000
b111110011 '
1&
1#
1"
0$
#5000000
0)
b111110100 '
0&
1$
#5010000
1)
b111110101 '
1&
0#
0%
0$
#5020000
0)
b111110110 '
0&
1#
1%
1$
#5030000
1)
b111110111 '
1&
0$
#5040000
b111111000 '
0&
0#
0%
1$
#5050000
b111111001 '
1&
1#
0$
#5060000
b111111010 '
0&
0"
1$
#5070000
b111111011 '
0#
1"
0$
#5080000
b111111100 '
1#
0"
1$
#5090000
b111111101 '
1&
0#
1"
0$
#5100000
b111111110 '
0&
0"
1$
#5110000
b111111111 '
1&
1#
1%
0$
#5120000
b1000000000 '
1"
0%
1$
#5130000
b1000000001 '
0"
1%
0$
#5140000
b1000000010 '
0&
0#
0%
1$
#5150000
b1000000011 '
1&
1#
1"
1%
0$
#5160000
b1000000100 '
0&
0"
1$
#5170000
b1000000101 '
0$
#5180000
b1000000110 '
1&
0%
1$
#5190000
b1000000111 '
0#
1"
0$
#5200000
0)
b1000001000 '
0&
1#
1%
1$
#5210000
1)
b1000001001 '
0"
0%
0$
#5220000
b1000001010 '
1&
0#
1%
1$
#5230000
b1000001011 '
0&
1"
0%
0$
#5240000
b1000001100 '
1#
0"
1%
1$
#5250000
b1000001101 '
1&
1"
0%
0$
#5260000
b1000001110 '
0"
1%
1$
#5270000
b1000001111 '
0&
0#
0$
#5280000
b1000010000 '
1&
0%
1$
#5290000
b1000010001 '
0&
0$
#5300000
b1000010010 '
1&
1%
1$
#5310000
b1000010011 '
0&
1"
0%
0$
#5320000
b1000010100 '
0"
1%
1$
#5330000
b1000010101 '
1&
1"
0%
0$
#5340000
b1000010110 '
0&
1#
0"
1$
#5350000
b1000010111 '
1&
1"
0$
#5360000
b1000011000 '
0"
1$
#5370000
b1000011001 '
1%
0$
#5380000
b1000011010 '
0&
0#
1"
1$
#5390000
b1000011011 '
1&
1#
0"
0%
0$
#5400000
b1000011100 '
1%
1$
#5410000
b1000011101 '
0&
0#
0%
0$
#5420000
b1000011110 '
1"
1$
#5430000
b1000011111 '
0"
0$
#5440000
b1000100000 '
1$
#5450000
b1000100001 '
1#
0$
#5460000
b1000100010 '
0#
1$
#5470000
b1000100011 '
1"
1%
0$
#5480000
b1000100100 '
1&
1$
#5490000
b1000100101 '
0&
0"
0%
0$
#5500000
b1000100110 '
1&
1"
1%
1$
#5510000
b1000100111 '
1#
0$
#5520000
b1000101000 '
0&
0#
0"
0%
1$
#5530000
b1000101001 '
1&
1#
1%
0$
#5540000
0)
b1000101010 '
0&
1"
1$
#5550000
1)
b1000101011 '
0#
0"
0%
0$
#5560000
b1000101100 '
1&
1"
1$
#5570000
b1000101101 '
0$
#5580000
b1000101110 '
0"
1%
1$
#5590000
b1000101111 '
0&
1#
1"
0%
0$
#5600000
b1000110000 '
0#
0"
1$
#5610000
b1000110001 '
1%
0$
#5620000
b1000110010 '
1#
1"
0%
1$
#5630000
b1000110011 '
0#
0"
1%
0$
#5640000
b1000110100 '
1&
1"
0%
1$
#5650000
b1000110101 '
0&
0$
#5660000
b1000110110 '
1#
0"
1%
1$
#5670000
b1000110111 '
1&
0%
0$
#5680000
b1000111000 '
0&
1%
1$
#5690000
b1000111001 '
1&
0$
#5700000
b1000111010 '
0&
1$
#5710000
b1000111011 '
1&
0#
1"
0%
0$
#5720000
b1000111100 '
0&
0"
1%
1$
#5730000
b1000111101 '
1#
1"
0%
0$
#5740000
b1000111110 '
1&
0"
1%
1$
#5750000
b1000111111 '
0&
0#
0%
0$
#5760000
b1001000000 '
1#
1"
1$
#5770000
0)
1(
b1001000001 '
1%
0$
#5780000
1)
0(
b1001000010 '
0%
1$
#5790000
b1001000011 '
0#
0"
0$
#5800000
b1001000100 '
1"
1$
#5810000
b1001000101 '
1&
1#
0$
#5820000
b1001000110 '
1%
1$
#5830000
b1001000111 '
0$
#5840000
b1001001000 '
0%
1$
#5850000
b1001001001 '
0&
0#
0"
0$
#5860000
b1001001010 '
1$
#5870000
b1001001011 '
1&
1"
1%
0$
#5880000
b1001001100 '
1$
#5890000
b1001001101 '
0&
0"
0$
#5900000
b1001001110 '
1&
1#
1"
0%
1$
#5910000
b1001001111 '
0#
0"
0$
#5920000
0)
b1001010000 '
0&
1#
1"
1%
1$
#5930000
1)
b1001010001 '
0#
0"
0%
0$
#5940000
0)
b1001010010 '
1#
1"
1%
1$
#5950000
1)
b1001010011 '
0%
0$
#5960000
b1001010100 '
1&
0#
1$
#5970000
b1001010101 '
0&
1#
0"
1%
0$
#5980000
b1001010110 '
0#
1"
0%
1$
#5990000
0)
1(
b1001010111 '
1#
1%
0$
#6000000
0(
b1001011000 '
1$
#6010000
1)
b1001011001 '
0"
0$
#6020000
b1001011010 '
1"
0%
1$
#6030000
0)
1(
b1001011011 '
1%
0$
#6040000
1)
0(
b1001011100 '
0#
0"
1$
#6050000
b1001011101 '
1&
1#
0$
#6060000
b1001011110 '
1"
1$
#6070000
b1001011111 '
0#
0%
0$
#6080000
b1001100000 '
0&
1#
1$
#6090000
b1001100001 '
0"
0$
#6100000
b1001100010 '
1&
1"
1%
1$
