Projeto 2 Final/Projeto2_Microondas/Projeto2_Microondas/microondas_nivel1/encoder_nivel2/nivel3/HDL/mux2_to_1.v
module mux2_to_1(output wire pgt_1Hz,
                input wire atraso,  Hz_1 , Sel);

assign pgt_1Hz = (Sel == 1'b0) ? atraso :
                 (Sel == 1'b1) ?  Hz_1 :
                 1'bX;

endmodule

Projeto 2 Final/Projeto2_Microondas/Projeto2_Microondas/microondas_nivel1/encoder_nivel2/nivel3/HDL/contador_7_n_reciclavel.v
module contador_7_n_reciclavel( 
    input wire Clock, Clear,
    output reg saida);

    reg [2:0] contador = 0;
/*
Como clear é ativo em nível alto, é preciso verificar também quando sua borda positiva chega,
além de ser necessário verificar o contador toda vez que a borda positiva do clock chega.
O contador recebe como entrada o clock e o clear, que vem do codificador e é ativado quando 
alguém tecla algum dígito.

Além disso, ele dá um atraso de 40 ms para evitar trepidação quando alguém clicar em alguma tecla.
Esse valor de 40 ms para tornar a saída positiva é dado na verificação "if(contador == 3)". Aqui,
é verificado se contador é igual a 3 porque ele está em um bloco sequencial, então contador será
incrementado para 4 na execução em que contador=3. 
*/ 
    always @(posedge Clock or posedge Clear) 
    begin
        if(Clear) begin
            saida <= 0;
            contador = 0;
        end
        else begin
            if(contador < 7) 
                contador <= contador + 1;
            if(contador == 3) 
                saida <=  1;
            else 
                saida <= 0;
        end
    end
endmodule

Projeto 2 Final/Projeto2_Microondas/Projeto2_Microondas/microondas_nivel1/encoder_nivel2/nivel3/HDL/divide_freq.v
module divide_freq (input wire clock,
                    output wire Hz1);

    reg [6:0] contador = 7'b0000000; 
    reg freq_1Hz = 0;
    assign Hz1 = freq_1Hz;

    always @(posedge clock) begin
        contador <= contador + 1; // "contador" será incrementado a cada borda positiva do relógio
        if (contador == 7'd99) begin // Quando contador=99, ele terá sido incrementado para 100
            freq_1Hz <= 1; // contador=100 indica que já foram 100 bordas positivas do relógio e se passou 1 segundo
            contador <= 0; // Para reiniciar o divisor de frequência, contador volta a ser 0
        end
        else begin
             freq_1Hz <= 0; // Se "contador" não for 100, então não se passou mais 1 segundo e a saída não pode ser 1
        end
    end 

endmodule

Projeto 2 Final/Projeto2_Microondas/Projeto2_Microondas/microondas_nivel1/encoder_nivel2/nivel3/HDL/priority_encoder.v
module priority_encoder(output reg [3:0] saidaBCD,
                        output wire loadn,
                        input wire [9:0] teclado, 
                        input wire enablen);

// Mapeamento de teclas usado                        
/*
IDLE = 0000000000 (SEM ENTRADAS NO TECLADO) 
0    = 0000000001
1    = 0000000010
2    = 0000000100
3    = 0000001000
4    = 0000010000
5    = 0000100000
6    = 0001000000
7    = 0010000000
8    = 0100000000
9    = 1000000000
*/
    // loadn será ativo em nível baixo, então ele só é 0 e ativa o contador_7_n_reciclável
    // quando enablen for 0 e alguma tecla está sendo pressionada
    assign loadn = (enablen | ~(teclado[0] | teclado[1] | teclado[2] | teclado[3] | teclado[4] | teclado[5] | teclado[6] | teclado[7] | teclado[8] | teclado[9]));
    always @(teclado) 
        begin
            casex (teclado)
                10'b0000000001 : saidaBCD = 4'b0000;
                10'b000000001x : saidaBCD = 4'b0001;
                10'b00000001xx : saidaBCD = 4'b0010;
                10'b0000001xxx : saidaBCD = 4'b0011;
                10'b000001xxxx : saidaBCD = 4'b0100;
                10'b00001xxxxx : saidaBCD = 4'b0101;
                10'b0001xxxxxx : saidaBCD = 4'b0110;
                10'b001xxxxxxx : saidaBCD = 4'b0111;
                10'b01xxxxxxxx : saidaBCD = 4'b1000;
                10'b1xxxxxxxxx : saidaBCD = 4'b1001;
                default: saidaBCD = 4'b0000;
            endcase
        end
endmodule

Projeto 2 Final/Projeto2_Microondas/Projeto2_Microondas/microondas_nivel1/encoder_nivel2/HDL/encoder.v
`include "../nivel3/HDL/contador_7_n_reciclavel.v"
`include "../nivel3/HDL/divide_freq.v"
`include "../nivel3/HDL/mux2_to_1.v"
`include "../nivel3/HDL/priority_encoder.v"


module encoder (output wire [3:0] D,
                output wire loadn, pgt_1Hz,
                input wire [9:0] teclado,
                input wire enablen, Hz_100_clock
                );

    wire borda_subida, clear, Hz1_clock; // Fios intermediários de dentro do próprio encoder, que 
                                        // servem para conectar os componentes de nível 3 entre si

    // Configurando o priority_encoder            
    priority_encoder codificador_prioritario(D, loadn, teclado, enablen);
    // Configurando o divide_freq
    divide_freq dividido_por_100(Hz_100_clock, Hz_1_clock);
    // Configurando o contador_7_n_reciclavel
    contador_7_n_reciclavel Atraso(Hz_100_clock, loadn, borda_subida);
    // Configurando o mux2_to_1
    mux2_to_1 MUX(pgt_1Hz, borda_subida, Hz_1_clock, enablen); // Recebe Hz_1_clock de divide_freq e 
                                                            // borda_subida de contador_7_n_reciclavel

endmodule

Projeto 2 Final/Projeto2_Microondas/Projeto2_Microondas/microondas_nivel1/encoder_nivel2/Testes/encoder_tb.v
`timescale 1ms/1ps
`include "../HDL/encoder.v"

module encoder_tb(); 

    reg  [9:0] teclado_tb;
    reg enablen_tb, Hz_100_clock_tb; 
    wire [3:0] D_tb;
    wire loadn_tb, pgt_1Hz_tb;

    
    integer i;
    

    encoder enc(.D(D_tb), .loadn(loadn_tb), .pgt_1Hz(pgt_1Hz_tb), .teclado(teclado_tb), .enablen(enablen_tb), .Hz_100_clock(Hz_100_clock_tb));

    initial begin
        $dumpfile("encoder_tb.vcd");
	    $dumpvars(0,encoder_tb);

        enablen_tb = 0; // enablen_tb inicial é 0, então ele já vai ativar, pois é ativo em nível baixo
        Hz_100_clock_tb = 1; // Para testar, o clock inicial foi 1 e ele ficará alternando
        teclado_tb = 10'b0000000000; // Estado inicial do teclado

        for(i = 0; i < 2200; i=i+1) begin
            #5 Hz_100_clock_tb <= ~Hz_100_clock_tb; // Alterna o relógio a cada 50ps
        end
        
    end

    initial begin
        #500 teclado_tb = 10'b0000000000; // Cada um desses é um dígito sendo clicado
        #500 teclado_tb = 10'b0000000001;
        #500 teclado_tb = 10'b0000000000;
        #500 teclado_tb = 10'b0000000010;
        #500 teclado_tb = 10'b0000000000;
        #500 teclado_tb = 10'b0000000100;
        #500 teclado_tb = 10'b0000000000;
        #500 teclado_tb = 10'b0000001000;
        #500 teclado_tb = 10'b0000000000;
        #500 teclado_tb = 10'b0000010000;
        #500 teclado_tb = 10'b0000000000;
        #500 teclado_tb = 10'b0000100000;
        #500 teclado_tb = 10'b0000000000;
        #500 teclado_tb = 10'b0001000000;
        #500 teclado_tb = 10'b0000000000;
        #500 teclado_tb = 10'b0010000000;
        #500 teclado_tb = 10'b0000000000;
        #500 teclado_tb = 10'b0100000000;
        #500 teclado_tb = 10'b0000000000;
        #500 teclado_tb = 10'b1000000000; enablen_tb = 1; // No enablen_tb desativa no final
    end

endmodule

Projeto 2 Final/Projeto2_Microondas/Projeto2_Microondas/microondas_nivel1/encoder_nivel2/Testes/encoder_tb.vcd
$date
	Sat Jul 23 16:57:45 2022
$end
$version
	Icarus Verilog
$end
$timescale
	1ps
$end
$scope module encoder_tb $end
$var wire 1 ! pgt_1Hz_tb $end
$var wire 1 " loadn_tb $end
$var wire 4 # D_tb [3:0] $end
$var reg 1 $ Hz_100_clock_tb $end
$var reg 1 % enablen_tb $end
$var reg 10 & teclado_tb [9:0] $end
$var integer 32 ' i [31:0] $end
$scope module enc $end
$var wire 1 $ Hz_100_clock $end
$var wire 1 % enablen $end
$var wire 10 ( teclado [9:0] $end
$var wire 1 ! pgt_1Hz $end
$var wire 1 " loadn $end
$var wire 1 ) borda_subida $end
$var wire 1 * Hz_1_clock $end
$var wire 4 + D [3:0] $end
$scope module Atraso $end
$var wire 1 $ Clock $end
$var wire 1 " Clear $end
$var reg 3 , contador [2:0] $end
$var reg 1 ) saida $end
$upscope $end
$scope module MUX $end
$var wire 1 % Sel $end
$var wire 1 ) atraso $end
$var wire 1 ! pgt_1Hz $end
$var wire 1 * Hz_1 $end
$upscope $end
$scope module codificador_prioritario $end
$var wire 1 % enablen $end
$var wire 1 " loadn $end
$var wire 10 - teclado [9:0] $end
$var reg 4 . saidaBCD [3:0] $end
$upscope $end
$scope module dividido_por_100 $end
$var wire 1 $ clock $end
$var wire 1 * Hz1 $end
$var reg 7 / contador [6:0] $end
$var reg 1 * freq_1Hz $end
$upscope $end
$upscope $end
$upscope $end
$enddefinitions $end
#0
$dumpvars
b1 /
b0 .
b0 -
b0 ,
b0 +
0*
0)
b0 (
b0 '
b0 &
0%
1$
b0 #
1"
0!
$end
#5000000000
0$
b1 '
#10000000000
b10 /
1$
b10 '
#15000000000
0$
b11 '
#20000000000
b11 /
1$
b100 '
#25000000000
0$
b101 '
#30000000000
b100 /
1$
b110 '
#35000000000
0$
b111 '
#40000000000
b101 /
1$
b1000 '
#45000000000
0$
b1001 '
#50000000000
b110 /
1$
b1010 '
#55000000000
0$
b1011 '
#60000000000
b111 /
1$
b1100 '
#65000000000
0$
b1101 '
#70000000000
b1000 /
1$
b1110 '
#75000000000
0$
b1111 '
#80000000000
b1001 /
1$
b10000 '
#85000000000
0$
b10001 '
#90000000000
b1010 /
1$
b10010 '
#95000000000
0$
b10011 '
#100000000000
b1011 /
1$
b10100 '
#105000000000
0$
b10101 '
#110000000000
b1100 /
1$
b10110 '
#115000000000
0$
b10111 '
#120000000000
b1101 /
1$
b11000 '
#125000000000
0$
b11001 '
#130000000000
b1110 /
1$
b11010 '
#135000000000
0$
b11011 '
#140000000000
b1111 /
1$
b11100 '
#145000000000
0$
b11101 '
#150000000000
b10000 /
1$
b11110 '
#155000000000
0$
b11111 '
#160000000000
b10001 /
1$
b100000 '
#165000000000
0$
b100001 '
#170000000000
b10010 /
1$
b100010 '
#175000000000
0$
b100011 '
#180000000000
b10011 /
1$
b100100 '
#185000000000
0$
b100101 '
#190000000000
b10100 /
1$
b100110 '
#195000000000
0$
b100111 '
#200000000000
b10101 /
1$
b101000 '
#205000000000
0$
b101001 '
#210000000000
b10110 /
1$
b101010 '
#215000000000
0$
b101011 '
#220000000000
b10111 /
1$
b101100 '
#225000000000
0$
b101101 '
#230000000000
b11000 /
1$
b101110 '
#235000000000
0$
b101111 '
#240000000000
b11001 /
1$
b110000 '
#245000000000
0$
b110001 '
#250000000000
b11010 /
1$
b110010 '
#255000000000
0$
b110011 '
#260000000000
b11011 /
1$
b110100 '
#265000000000
0$
b110101 '
#270000000000
b11100 /
1$
b110110 '
#275000000000
0$
b110111 '
#280000000000
b11101 /
1$
b111000 '
#285000000000
0$
b111001 '
#290000000000
b11110 /
1$
b111010 '
#295000000000
0$
b111011 '
#300000000000
b11111 /
1$
b111100 '
#305000000000
0$
b111101 '
#310000000000
b100000 /
1$
b111110 '
#315000000000
0$
b111111 '
#320000000000
b100001 /
1$
b1000000 '
#325000000000
0$
b1000001 '
#330000000000
b100010 /
1$
b1000010 '
#335000000000
0$
b1000011 '
#340000000000
b100011 /
1$
b1000100 '
#345000000000
0$
b1000101 '
#350000000000
b100100 /
1$
b1000110 '
#355000000000
0$
b1000111 '
#360000000000
b100101 /
1$
b1001000 '
#365000000000
0$
b1001001 '
#370000000000
b100110 /
1$
b1001010 '
#375000000000
0$
b1001011 '
#380000000000
b100111 /
1$
b1001100 '
#385000000000
0$
b1001101 '
#390000000000
b101000 /
1$
b1001110 '
#395000000000
0$
b1001111 '
#400000000000
b101001 /
1$
b1010000 '
#405000000000
0$
b1010001 '
#410000000000
b101010 /
1$
b1010010 '
#415000000000
0$
b1010011 '
#420000000000
b101011 /
1$
b1010100 '
#425000000000
0$
b1010101 '
#430000000000
b101100 /
1$
b1010110 '
#435000000000
0$
b1010111 '
#440000000000
b101101 /
1$
b1011000 '
#445000000000
0$
b1011001 '
#450000000000
b101110 /
1$
b1011010 '
#455000000000
0$
b1011011 '
#460000000000
b101111 /
1$
b1011100 '
#465000000000
0$
b1011101 '
#470000000000
b110000 /
1$
b1011110 '
#475000000000
0$
b1011111 '
#480000000000
b110001 /
1$
b1100000 '
#485000000000
0$
b1100001 '
#490000000000
b110010 /
1$
b1100010 '
#495000000000
0$
b1100011 '
#500000000000
b110011 /
1$
b1100100 '
#505000000000
0$
b1100101 '
#510000000000
b110100 /
1$
b1100110 '
#515000000000
0$
b1100111 '
#520000000000
b110101 /
1$
b1101000 '
#525000000000
0$
b1101001 '
#530000000000
b110110 /
1$
b1101010 '
#535000000000
0$
b1101011 '
#540000000000
b110111 /
1$
b1101100 '
#545000000000
0$
b1101101 '
#550000000000
b111000 /
1$
b1101110 '
#555000000000
0$
b1101111 '
#560000000000
b111001 /
1$
b1110000 '
#565000000000
0$
b1110001 '
#570000000000
b111010 /
1$
b1110010 '
#575000000000
0$
b1110011 '
#580000000000
b111011 /
1$
b1110100 '
#585000000000
0$
b1110101 '
#590000000000
b111100 /
1$
b1110110 '
#595000000000
0$
b1110111 '
#600000000000
b111101 /
1$
b1111000 '
#605000000000
0$
b1111001 '
#610000000000
b111110 /
1$
b1111010 '
#615000000000
0$
b1111011 '
#620000000000
b111111 /
1$
b1111100 '
#625000000000
0$
b1111101 '
#630000000000
b1000000 /
1$
b1111110 '
#635000000000
0$
b1111111 '
#640000000000
b1000001 /
1$
b10000000 '
#645000000000
0$
b10000001 '
#650000000000
b1000010 /
1$
b10000010 '
#655000000000
0$
b10000011 '
#660000000000
b1000011 /
1$
b10000100 '
#665000000000
0$
b10000101 '
#670000000000
b1000100 /
1$
b10000110 '
#675000000000
0$
b10000111 '
#680000000000
b1000101 /
1$
b10001000 '
#685000000000
0$
b10001001 '
#690000000000
b1000110 /
1$
b10001010 '
#695000000000
0$
b10001011 '
#700000000000
b1000111 /
1$
b10001100 '
#705000000000
0$
b10001101 '
#710000000000
b1001000 /
1$
b10001110 '
#715000000000
0$
b10001111 '
#720000000000
b1001001 /
1$
b10010000 '
#725000000000
0$
b10010001 '
#730000000000
b1001010 /
1$
b10010010 '
#735000000000
0$
b10010011 '
#740000000000
b1001011 /
1$
b10010100 '
#745000000000
0$
b10010101 '
#750000000000
b1001100 /
1$
b10010110 '
#755000000000
0$
b10010111 '
#760000000000
b1001101 /
1$
b10011000 '
#765000000000
0$
b10011001 '
#770000000000
b1001110 /
1$
b10011010 '
#775000000000
0$
b10011011 '
#780000000000
b1001111 /
1$
b10011100 '
#785000000000
0$
b10011101 '
#790000000000
b1010000 /
1$
b10011110 '
#795000000000
0$
b10011111 '
#800000000000
b1010001 /
1$
b10100000 '
#805000000000
0$
b10100001 '
#810000000000
b1010010 /
1$
b10100010 '
#815000000000
0$
b10100011 '
#820000000000
b1010011 /
1$
b10100100 '
#825000000000
0$
b10100101 '
#830000000000
b1010100 /
1$
b10100110 '
#835000000000
0$
b10100111 '
#840000000000
b1010101 /
1$
b10101000 '
#845000000000
0$
b10101001 '
#850000000000
b1010110 /
1$
b10101010 '
#855000000000
0$
b10101011 '
#860000000000
b1010111 /
1$
b10101100 '
#865000000000
0$
b10101101 '
#870000000000
b1011000 /
1$
b10101110 '
#875000000000
0$
b10101111 '
#880000000000
b1011001 /
1$
b10110000 '
#885000000000
0$
b10110001 '
#890000000000
b1011010 /
1$
b10110010 '
#895000000000
0$
b10110011 '
#900000000000
b1011011 /
1$
b10110100 '
#905000000000
0$
b10110101 '
#910000000000
b1011100 /
1$
b10110110 '
#915000000000
0$
b10110111 '
#920000000000
b1011101 /
1$
b10111000 '
#925000000000
0$
b10111001 '
#930000000000
b1011110 /
1$
b10111010 '
#935000000000
0$
b10111011 '
#940000000000
b1011111 /
1$
b10111100 '
#945000000000
0$
b10111101 '
#950000000000
b1100000 /
1$
b10111110 '
#955000000000
0$
b10111111 '
#960000000000
b1100001 /
1$
b11000000 '
#965000000000
0$
b11000001 '
#970000000000
b1100010 /
1$
b11000010 '
#975000000000
0$
b11000011 '
#980000000000
b1100011 /
1$
b11000100 '
#985000000000
0$
b11000101 '
#990000000000
1*
b0 /
1$
b11000110 '
#995000000000
0$
b11000111 '
#1000000000000
b1 ,
0*
b1 /
1$
0"
b11001000 '
b1 &
b1 (
b1 -
#1005000000000
0$
b11001001 '
#1010000000000
b10 ,
b10 /
1$
b11001010 '
#1015000000000
0$
b11001011 '
#1020000000000
b11 ,
b11 /
1$
b11001100 '
#1025000000000
0$
b11001101 '
#1030000000000
1!
1)
b100 ,
b100 /
1$
b11001110 '
#1035000000000
0$
b11001111 '
#1040000000000
0!
0)
b101 ,
b101 /
1$
b11010000 '
#1045000000000
0$
b11010001 '
#1050000000000
b110 ,
b110 /
1$
b11010010 '
#1055000000000
0$
b11010011 '
#1060000000000
b111 ,
b111 /
1$
b11010100 '
#1065000000000
0$
b11010101 '
#1070000000000
b1000 /
1$
b11010110 '
#1075000000000
0$
b11010111 '
#1080000000000
b1001 /
1$
b11011000 '
#1085000000000
0$
b11011001 '
#1090000000000
b1010 /
1$
b11011010 '
#1095000000000
0$
b11011011 '
#1100000000000
b1011 /
1$
b11011100 '
#1105000000000
0$
b11011101 '
#1110000000000
b1100 /
1$
b11011110 '
#1115000000000
0$
b11011111 '
#1120000000000
b1101 /
1$
b11100000 '
#1125000000000
0$
b11100001 '
#1130000000000
b1110 /
1$
b11100010 '
#1135000000000
0$
b11100011 '
#1140000000000
b1111 /
1$
b11100100 '
#1145000000000
0$
b11100101 '
#1150000000000
b10000 /
1$
b11100110 '
#1155000000000
0$
b11100111 '
#1160000000000
b10001 /
1$
b11101000 '
#1165000000000
0$
b11101001 '
#1170000000000
b10010 /
1$
b11101010 '
#1175000000000
0$
b11101011 '
#1180000000000
b10011 /
1$
b11101100 '
#1185000000000
0$
b11101101 '
#1190000000000
b10100 /
1$
b11101110 '
#1195000000000
0$
b11101111 '
#1200000000000
b10101 /
1$
b11110000 '
#1205000000000
0$
b11110001 '
#1210000000000
b10110 /
1$
b11110010 '
#1215000000000
0$
b11110011 '
#1220000000000
b10111 /
1$
b11110100 '
#1225000000000
0$
b11110101 '
#1230000000000
b11000 /
1$
b11110110 '
#1235000000000
0$
b11110111 '
#1240000000000
b11001 /
1$
b11111000 '
#1245000000000
0$
b11111001 '
#1250000000000
b11010 /
1$
b11111010 '
#1255000000000
0$
b11111011 '
#1260000000000
b11011 /
1$
b11111100 '
#1265000000000
0$
b11111101 '
#1270000000000
b11100 /
1$
b11111110 '
#1275000000000
0$
b11111111 '
#1280000000000
b11101 /
1$
b100000000 '
#1285000000000
0$
b100000001 '
#1290000000000
b11110 /
1$
b100000010 '
#1295000000000
0$
b100000011 '
#1300000000000
b11111 /
1$
b100000100 '
#1305000000000
0$
b100000101 '
#1310000000000
b100000 /
1$
b100000110 '
#1315000000000
0$
b100000111 '
#1320000000000
b100001 /
1$
b100001000 '
#1325000000000
0$
b100001001 '
#1330000000000
b100010 /
1$
b100001010 '
#1335000000000
0$
b100001011 '
#1340000000000
b100011 /
1$
b100001100 '
#1345000000000
0$
b100001101 '
#1350000000000
b100100 /
1$
b100001110 '
#1355000000000
0$
b100001111 '
#1360000000000
b100101 /
1$
b100010000 '
#1365000000000
0$
b100010001 '
#1370000000000
b100110 /
1$
b100010010 '
#1375000000000
0$
b100010011 '
#1380000000000
b100111 /
1$
b100010100 '
#1385000000000
0$
b100010101 '
#1390000000000
b101000 /
1$
b100010110 '
#1395000000000
0$
b100010111 '
#1400000000000
b101001 /
1$
b100011000 '
#1405000000000
0$
b100011001 '
#1410000000000
b101010 /
1$
b100011010 '
#1415000000000
0$
b100011011 '
#1420000000000
b101011 /
1$
b100011100 '
#1425000000000
0$
b100011101 '
#1430000000000
b101100 /
1$
b100011110 '
#1435000000000
0$
b100011111 '
#1440000000000
b101101 /
1$
b100100000 '
#1445000000000
0$
b100100001 '
#1450000000000
b101110 /
1$
b100100010 '
#1455000000000
0$
b100100011 '
#1460000000000
b101111 /
1$
b100100100 '
#1465000000000
0$
b100100101 '
#1470000000000
b110000 /
1$
b100100110 '
#1475000000000
0$
b100100111 '
#1480000000000
b110001 /
1$
b100101000 '
#1485000000000
0$
b100101001 '
#1490000000000
b110010 /
1$
b100101010 '
#1495000000000
0$
b100101011 '
#1500000000000
b110011 /
b0 ,
1$
1"
b100101100 '
b0 &
b0 (
b0 -
#1505000000000
0$
b100101101 '
#1510000000000
b110100 /
1$
b100101110 '
#1515000000000
0$
b100101111 '
#1520000000000
b110101 /
1$
b100110000 '
#1525000000000
0$
b100110001 '
#1530000000000
b110110 /
1$
b100110010 '
#1535000000000
0$
b100110011 '
#1540000000000
b110111 /
1$
b100110100 '
#1545000000000
0$
b100110101 '
#1550000000000
b111000 /
1$
b100110110 '
#1555000000000
0$
b100110111 '
#1560000000000
b111001 /
1$
b100111000 '
#1565000000000
0$
b100111001 '
#1570000000000
b111010 /
1$
b100111010 '
#1575000000000
0$
b100111011 '
#1580000000000
b111011 /
1$
b100111100 '
#1585000000000
0$
b100111101 '
#1590000000000
b111100 /
1$
b100111110 '
#1595000000000
0$
b100111111 '
#1600000000000
b111101 /
1$
b101000000 '
#1605000000000
0$
b101000001 '
#1610000000000
b111110 /
1$
b101000010 '
#1615000000000
0$
b101000011 '
#1620000000000
b111111 /
1$
b101000100 '
#1625000000000
0$
b101000101 '
#1630000000000
b1000000 /
1$
b101000110 '
#1635000000000
0$
b101000111 '
#1640000000000
b1000001 /
1$
b101001000 '
#1645000000000
0$
b101001001 '
#1650000000000
b1000010 /
1$
b101001010 '
#1655000000000
0$
b101001011 '
#1660000000000
b1000011 /
1$
b101001100 '
#1665000000000
0$
b101001101 '
#1670000000000
b1000100 /
1$
b101001110 '
#1675000000000
0$
b101001111 '
#1680000000000
b1000101 /
1$
b101010000 '
#1685000000000
0$
b101010001 '
#1690000000000
b1000110 /
1$
b101010010 '
#1695000000000
0$
b101010011 '
#1700000000000
b1000111 /
1$
b101010100 '
#1705000000000
0$
b101010101 '
#1710000000000
b1001000 /
1$
b101010110 '
#1715000000000
0$
b101010111 '
#1720000000000
b1001001 /
1$
b101011000 '
#1725000000000
0$
b101011001 '
#1730000000000
b1001010 /
1$
b101011010 '
#1735000000000
0$
b101011011 '
#1740000000000
b1001011 /
1$
b101011100 '
#1745000000000
0$
b101011101 '
#1750000000000
b1001100 /
1$
b101011110 '
#1755000000000
0$
b101011111 '
#1760000000000
b1001101 /
1$
b101100000 '
#1765000000000
0$
b101100001 '
#1770000000000
b1001110 /
1$
b101100010 '
#1775000000000
0$
b101100011 '
#1780000000000
b1001111 /
1$
b101100100 '
#1785000000000
0$
b101100101 '
#1790000000000
b1010000 /
1$
b101100110 '
#1795000000000
0$
b101100111 '
#1800000000000
b1010001 /
1$
b101101000 '
#1805000000000
0$
b101101001 '
#1810000000000
b1010010 /
1$
b101101010 '
#1815000000000
0$
b101101011 '
#1820000000000
b1010011 /
1$
b101101100 '
#1825000000000
0$
b101101101 '
#1830000000000
b1010100 /
1$
b101101110 '
#1835000000000
0$
b101101111 '
#1840000000000
b1010101 /
1$
b101110000 '
#1845000000000
0$
b101110001 '
#1850000000000
b1010110 /
1$
b101110010 '
#1855000000000
0$
b101110011 '
#1860000000000
b1010111 /
1$
b101110100 '
#1865000000000
0$
b101110101 '
#1870000000000
b1011000 /
1$
b101110110 '
#1875000000000
0$
b101110111 '
#1880000000000
b1011001 /
1$
b101111000 '
#1885000000000
0$
b101111001 '
#1890000000000
b1011010 /
1$
b101111010 '
#1895000000000
0$
b101111011 '
#1900000000000
b1011011 /
1$
b101111100 '
#1905000000000
0$
b101111101 '
#1910000000000
b1011100 /
1$
b101111110 '
#1915000000000
0$
b101111111 '
#1920000000000
b1011101 /
1$
b110000000 '
#1925000000000
0$
b110000001 '
#1930000000000
b1011110 /
1$
b110000010 '
#1935000000000
0$
b110000011 '
#1940000000000
b1011111 /
1$
b110000100 '
#1945000000000
0$
b110000101 '
#1950000000000
b1100000 /
1$
b110000110 '
#1955000000000
0$
b110000111 '
#1960000000000
b1100001 /
1$
b110001000 '
#1965000000000
0$
b110001001 '
#1970000000000
b1100010 /
1$
b110001010 '
#1975000000000
0$
b110001011 '
#1980000000000
b1100011 /
1$
b110001100 '
#1985000000000
0$
b110001101 '
#1990000000000
1*
b0 /
1$
b110001110 '
#1995000000000
0$
b110001111 '
#2000000000000
b1 ,
0*
b1 /
1$
0"
b1 #
b1 +
b1 .
b110010000 '
b10 &
b10 (
b10 -
#2005000000000
0$
b110010001 '
#2010000000000
b10 ,
b10 /
1$
b110010010 '
#2015000000000
0$
b110010011 '
#2020000000000
b11 ,
b11 /
1$
b110010100 '
#2025000000000
0$
b110010101 '
#2030000000000
1!
1)
b100 ,
b100 /
1$
b110010110 '
#2035000000000
0$
b110010111 '
#2040000000000
0!
0)
b101 ,
b101 /
1$
b110011000 '
#2045000000000
0$
b110011001 '
#2050000000000
b110 ,
b110 /
1$
b110011010 '
#2055000000000
0$
b110011011 '
#2060000000000
b111 ,
b111 /
1$
b110011100 '
#2065000000000
0$
b110011101 '
#2070000000000
b1000 /
1$
b110011110 '
#2075000000000
0$
b110011111 '
#2080000000000
b1001 /
1$
b110100000 '
#2085000000000
0$
b110100001 '
#2090000000000
b1010 /
1$
b110100010 '
#2095000000000
0$
b110100011 '
#2100000000000
b1011 /
1$
b110100100 '
#2105000000000
0$
b110100101 '
#2110000000000
b1100 /
1$
b110100110 '
#2115000000000
0$
b110100111 '
#2120000000000
b1101 /
1$
b110101000 '
#2125000000000
0$
b110101001 '
#2130000000000
b1110 /
1$
b110101010 '
#2135000000000
0$
b110101011 '
#2140000000000
b1111 /
1$
b110101100 '
#2145000000000
0$
b110101101 '
#2150000000000
b10000 /
1$
b110101110 '
#2155000000000
0$
b110101111 '
#2160000000000
b10001 /
1$
b110110000 '
#2165000000000
0$
b110110001 '
#2170000000000
b10010 /
1$
b110110010 '
#2175000000000
0$
b110110011 '
#2180000000000
b10011 /
1$
b110110100 '
#2185000000000
0$
b110110101 '
#2190000000000
b10100 /
1$
b110110110 '
#2195000000000
0$
b110110111 '
#2200000000000
b10101 /
1$
b110111000 '
#2205000000000
0$
b110111001 '
#2210000000000
b10110 /
1$
b110111010 '
#2215000000000
0$
b110111011 '
#2220000000000
b10111 /
1$
b110111100 '
#2225000000000
0$
b110111101 '
#2230000000000
b11000 /
1$
b110111110 '
#2235000000000
0$
b110111111 '
#2240000000000
b11001 /
1$
b111000000 '
#2245000000000
0$
b111000001 '
#2250000000000
b11010 /
1$
b111000010 '
#2255000000000
0$
b111000011 '
#2260000000000
b11011 /
1$
b111000100 '
#2265000000000
0$
b111000101 '
#2270000000000
b11100 /
1$
b111000110 '
#2275000000000
0$
b111000111 '
#2280000000000
b11101 /
1$
b111001000 '
#2285000000000
0$
b111001001 '
#2290000000000
b11110 /
1$
b111001010 '
#2295000000000
0$
b111001011 '
#2300000000000
b11111 /
1$
b111001100 '
#2305000000000
0$
b111001101 '
#2310000000000
b100000 /
1$
b111001110 '
#2315000000000
0$
b111001111 '
#2320000000000
b100001 /
1$
b111010000 '
#2325000000000
0$
b111010001 '
#2330000000000
b100010 /
1$
b111010010 '
#2335000000000
0$
b111010011 '
#2340000000000
b100011 /
1$
b111010100 '
#2345000000000
0$
b111010101 '
#2350000000000
b100100 /
1$
b111010110 '
#2355000000000
0$
b111010111 '
#2360000000000
b100101 /
1$
b111011000 '
#2365000000000
0$
b111011001 '
#2370000000000
b100110 /
1$
b111011010 '
#2375000000000
0$
b111011011 '
#2380000000000
b100111 /
1$
b111011100 '
#2385000000000
0$
b111011101 '
#2390000000000
b101000 /
1$
b111011110 '
#2395000000000
0$
b111011111 '
#2400000000000
b101001 /
1$
b111100000 '
#2405000000000
0$
b111100001 '
#2410000000000
b101010 /
1$
b111100010 '
#2415000000000
0$
b111100011 '
#2420000000000
b101011 /
1$
b111100100 '
#2425000000000
0$
b111100101 '
#2430000000000
b101100 /
1$
b111100110 '
#2435000000000
0$
b111100111 '
#2440000000000
b101101 /
1$
b111101000 '
#2445000000000
0$
b111101001 '
#2450000000000
b101110 /
1$
b111101010 '
#2455000000000
0$
b111101011 '
#2460000000000
b101111 /
1$
b111101100 '
#2465000000000
0$
b111101101 '
#2470000000000
b110000 /
1$
b111101110 '
#2475000000000
0$
b111101111 '
#2480000000000
b110001 /
1$
b111110000 '
#2485000000000
0$
b111110001 '
#2490000000000
b110010 /
1$
b111110010 '
#2495000000000
0$
b111110011 '
#2500000000000
b110011 /
b0 ,
1$
1"
b0 #
b0 +
b0 .
b111110100 '
b0 &
b0 (
b0 -
#2505000000000
0$
b111110101 '
#2510000000000
b110100 /
1$
b111110110 '
#2515000000000
0$
b111110111 '
#2520000000000
b110101 /
1$
b111111000 '
#2525000000000
0$
b111111001 '
#2530000000000
b110110 /
1$
b111111010 '
#2535000000000
0$
b111111011 '
#2540000000000
b110111 /
1$
b111111100 '
#2545000000000
0$
b111111101 '
#2550000000000
b111000 /
1$
b111111110 '
#2555000000000
0$
b111111111 '
#2560000000000
b111001 /
1$
b1000000000 '
#2565000000000
0$
b1000000001 '
#2570000000000
b111010 /
1$
b1000000010 '
#2575000000000
0$
b1000000011 '
#2580000000000
b111011 /
1$
b1000000100 '
#2585000000000
0$
b1000000101 '
#2590000000000
b111100 /
1$
b1000000110 '
#2595000000000
0$
b1000000111 '
#2600000000000
b111101 /
1$
b1000001000 '
#2605000000000
0$
b1000001001 '
#2610000000000
b111110 /
1$
b1000001010 '
#2615000000000
0$
b1000001011 '
#2620000000000
b111111 /
1$
b1000001100 '
#2625000000000
0$
b1000001101 '
#2630000000000
b1000000 /
1$
b1000001110 '
#2635000000000
0$
b1000001111 '
#2640000000000
b1000001 /
1$
b1000010000 '
#2645000000000
0$
b1000010001 '
#2650000000000
b1000010 /
1$
b1000010010 '
#2655000000000
0$
b1000010011 '
#2660000000000
b1000011 /
1$
b1000010100 '
#2665000000000
0$
b1000010101 '
#2670000000000
b1000100 /
1$
b1000010110 '
#2675000000000
0$
b1000010111 '
