quartus/decoder/decoder_7.v
module decoder_7(output wire [6:0] sec_ones_segs, sec_tens_segs, mins_segs,
                input wire  [3:0] sec_ones,sec_tens,min);

/*
O relógio do segmento está dividido em 3 partes: a dos segundos, a das dezenas de segundos 
e a dos minutos.
O segmento dos segundos recebe sec_ones e dá como resultado sec_ones_segs;
O segmento das dezenas de segundos recebe sec_tens e dá como resultado sec_tens_segs;
O segmento dos minutos recebe mins e dá como resultado mins_segs;
Cada um dos assign's a seguir decodifica um código BCD recebido para o código de 7 dígitos 
do segmento correspondente.
*/
assign sec_ones_segs =  (sec_ones == 4'b0000) ? 7'b100_0000:
                        (sec_ones == 4'b0001) ? 7'b111_1001:
                        (sec_ones == 4'b0010) ? 7'b010_0100:
                        (sec_ones == 4'b0011) ? 7'b011_0000:
                        (sec_ones == 4'b0100) ? 7'b001_1001:
                        (sec_ones == 4'b0101) ? 7'b001_0010:
                        (sec_ones == 4'b0110) ? 7'b000_0010:
                        (sec_ones == 4'b0111) ? 7'b111_1000:
                        (sec_ones == 4'b1000) ? 7'b000_0000:
                        (sec_ones == 4'b1001) ? 7'b001_0000:
                        8'bXXXX_XXXX;


assign sec_tens_segs =  (sec_tens == 4'b0000) ? 7'b100_0000:
                        (sec_tens == 4'b0001) ? 7'b111_1001:
                        (sec_tens == 4'b0010) ? 7'b010_0100:
                        (sec_tens == 4'b0011) ? 7'b011_0000:
                        (sec_tens == 4'b0100) ? 7'b001_1001:
                        (sec_tens == 4'b0101) ? 7'b001_0010:
                        (sec_tens == 4'b0110) ? 7'b000_0010:
                        (sec_tens == 4'b0111) ? 7'b111_1000:
                        (sec_tens == 4'b1000) ? 7'b000_0000:
                        (sec_tens == 4'b1001) ? 7'b001_0000:
                        8'bXXXX_XXXX;

assign mins_segs =   (min == 4'b0000)? 7'b100_0000:
                    (min == 4'b0001) ? 7'b111_1001:
                    (min == 4'b0010) ? 7'b010_0100:
                    (min == 4'b0011) ? 7'b011_0000:
                    (min == 4'b0100) ? 7'b001_1001:
                    (min == 4'b0101) ? 7'b001_0010:
                    (min == 4'b0110) ? 7'b000_0010:
                    (min == 4'b0111) ? 7'b111_1000:
                    (min == 4'b1000) ? 7'b000_0000:
                    (min == 4'b1001) ? 7'b001_0000:
                    8'bXXXX_XXXX;


endmodule

Projeto 2 Final/Projeto2_Microondas/Projeto2_Microondas/microondas_nivel1/decoder_nivel2/Teste/decoder_7_tb.v
`timescale 1ns/1ps
`include "../HDL/decoder_7.v"

module decoder_7_tb();
 
    reg [3:0] sec_ones_tb,sec_tens_tb,min_tb;

    wire [6:0] sec_ones_segs_tb, sec_tens_segs_tb, mins_segs_tb;
    
    
    decoder_7 DUT(.sec_ones(sec_ones_tb), .sec_tens(sec_tens_tb), .min(min_tb));
    
/*
O teste feito insere os valores de 0 a 9 na entrada sec_ones do decoder_7.v
*/    
    initial
    begin
        $dumpfile("decoder_7_tb.vcd");
        $dumpvars(0, decoder_7_tb);
            sec_ones_tb = 0; sec_tens_tb = 0; min_tb = 0; 
        #10 sec_ones_tb = 1; sec_tens_tb = 0; min_tb = 0; 
        #10 sec_ones_tb = 2; sec_tens_tb = 0; min_tb = 0; 
        #10 sec_ones_tb = 3; sec_tens_tb = 0; min_tb = 0; 
        #10 sec_ones_tb = 4; sec_tens_tb = 0; min_tb = 0; 
        #10 sec_ones_tb = 5; sec_tens_tb = 0; min_tb = 0; 
        #10 sec_ones_tb = 6; sec_tens_tb = 0; min_tb = 0; 
        #10 sec_ones_tb = 7; sec_tens_tb = 0; min_tb = 0; 
        #10 sec_ones_tb = 8; sec_tens_tb = 0; min_tb = 0; 
        #10 sec_ones_tb = 9; sec_tens_tb = 0; min_tb = 0;
        #10;
    end
endmodule

Projeto 2 Final/Projeto2_Microondas/Projeto2_Microondas/microondas_nivel1/decoder_nivel2/Teste/decoder_7_tb.vcd
$date
	Sat Jul 23 15:40:33 2022
$end
$version
	Icarus Verilog
$end
$timescale
	1ps
$end
$scope module decoder_7_tb $end
$var reg 4 ! min_tb [3:0] $end
$var reg 4 " sec_ones_tb [3:0] $end
$var reg 4 # sec_tens_tb [3:0] $end
$scope module DUT $end
$var wire 4 $ min [3:0] $end
$var wire 4 % sec_ones [3:0] $end
$var wire 4 & sec_tens [3:0] $end
$var wire 7 ' sec_tens_segs [6:0] $end
$var wire 7 ( sec_ones_segs [6:0] $end
$var wire 7 ) mins_segs [6:0] $end
$upscope $end
$upscope $end
$enddefinitions $end
#0
$dumpvars
b1111110 )
b1111110 (
b1111110 '
b0 &
b0 %
b0 $
b0 #
b0 "
b0 !
$end
#10000
b110000 (
b1 "
b1 %
#20000
b1101101 (
b10 "
b10 %
#30000
b1111001 (
b11 "
b11 %
#40000
b110011 (
b100 "
b100 %
#50000
b1011011 (
b101 "
b101 %
#60000
b1011111 (
b110 "
b110 %
#70000
b1110000 (
b111 "
b111 %
#80000
b1111111 (
b1000 "
b1000 %
#90000
b1110011 (
b1001 "
b1001 %
