microwave_level1/microwave_level1/control_level2/level-3/encoder_dec_to_bcd.v
module encoder_dec_to_bcd(input wire [9:0] DEC, input wire EN_N,
                          output reg [3:0] BCD, output wire LOAD_N);

    assign LOAD_N = (EN_N) | (DEC == 10'b0000000000);

    always @(DEC) begin

        if(!EN_N) begin
            casex (DEC)
                10'b0000000001: BCD = 4'b0000;
                10'b000000001x: BCD = 4'b0001;
                10'b00000001xx: BCD = 4'b0010;
                10'b0000001xxx: BCD = 4'b0011;
                10'b000001xxxx: BCD = 4'b0100;
                10'b00001xxxxx: BCD = 4'b0101;
                10'b0001xxxxxx: BCD = 4'b0110;
                10'b001xxxxxxx: BCD = 4'b0111;
                10'b01xxxxxxxx: BCD = 4'b1000;
                10'b1xxxxxxxxx: BCD = 4'b1001;
            default:
                BCD = 4'b0000;
            endcase
        end
    end
endmodule

microwave_level1/microwave_level1/control_level2/level-3/encoder_dec_to_bcd_tb.v
`include "encoder_dec_to_bcd.v"

module encoder_dec_to_bcd_tb();
    reg [9:0] DEC;
    reg EN;
    wire [3:0] BCD;
    wire DATA_VALID;

    encoder_dec_to_bcd dut(DEC, EN, BCD, DATA_VALID);

    initial begin
        EN = 0; #10;
        DEC = 10'b0000000001; #10;
        DEC = 10'b0000000010; #10;
        DEC = 10'b0000000100; #10;
        DEC = 10'b0000001000; #10;
        DEC = 10'b0000010000; #10;
        DEC = 10'b0000100000; #10;
        DEC = 10'b0001000000; #10;
        DEC = 10'b0010000000; #10;
        DEC = 10'b0100000000; #10;
        DEC = 10'b1000000000; #10;

        DEC = 10'b0000000000; #10;

        EN = 1; #10;
        DEC = 10'b0000000001; #10;
        DEC = 10'b0000000010; #10;
        DEC = 10'b0000000100; #10;
        DEC = 10'b0000001000; #10;
        DEC = 10'b0000010000; #10;
        DEC = 10'b0000100000; #10;
        DEC = 10'b0001000000; #10;
        DEC = 10'b0010000000; #10;
        DEC = 10'b0100000000; #10;
        DEC = 10'b1000000000; #10;

        DEC = 10'b0000000000; #10;

        EN = 0; #10;
        DEC = 10'b0000100001; #10;
        DEC = 10'b0000000010; #10;
        DEC = 10'b1000000100; #10;
        DEC = 10'b0000001000; #10;
        DEC = 10'b0000010000; #10;
        DEC = 10'b0000101000; #10;
        DEC = 10'b0001000000; #10;
        DEC = 10'b0010000000; #10;
        DEC = 10'b0100000000; #10;
        DEC = 10'b1000000001; #10;

        DEC = 10'b0000000000; #10;
    end


    initial begin
        $dumpfile("encoder_dec_to_bcd_tb.vcd");
        $dumpvars(0, encoder_dec_to_bcd_tb);
    end

endmodule

microwave_level1/microwave_level1/control_level2/level-3/encoder_dec_to_bcd_tb.vcd
$date
	Wed May 11 22:02:26 2022
$end
$version
	Icarus Verilog
$end
$timescale
	1s
$end
$scope module encoder_dec_to_bcd_tb $end
$var wire 1 ! DATA_VALID $end
$var wire 4 " BCD [3:0] $end
$var reg 10 # DEC [9:0] $end
$var reg 1 $ EN $end
$scope module dut $end
$var wire 10 % DEC [9:0] $end
$var wire 1 $ EN_N $end
$var wire 1 ! LOAD_N $end
$var reg 4 & BCD [3:0] $end
$upscope $end
$upscope $end
$enddefinitions $end
#0
$dumpvars
bx &
bx %
0$
bx #
bx "
x!
$end
#10
b0 "
b0 &
0!
b1 #
b1 %
#20
b1 "
b1 &
b10 #
b10 %
#30
b10 "
b10 &
b100 #
b100 %
#40
b11 "
b11 &
b1000 #
b1000 %
#50
b100 "
b100 &
b10000 #
b10000 %
#60
b101 "
b101 &
b100000 #
b100000 %
#70
b110 "
b110 &
b1000000 #
b1000000 %
#80
b111 "
b111 &
b10000000 #
b10000000 %
#90
b1000 "
b1000 &
b100000000 #
b100000000 %
#100
b1001 "
b1001 &
b1000000000 #
b1000000000 %
#110
b0 "
b0 &
1!
b0 #
b0 %
#120
1$
#130
b1 #
b1 %
#140
b10 #
b10 %
#150
b100 #
b100 %
#160
b1000 #
b1000 %
#170
b10000 #
b10000 %
#180
b100000 #
b100000 %
#190
b1000000 #
b1000000 %
#200
b10000000 #
b10000000 %
#210
b100000000 #
b100000000 %
#220
b1000000000 #
b1000000000 %
#230
b0 #
b0 %
#240
0$
#250
b101 "
b101 &
0!
b100001 #
b100001 %
#260
b1 "
b1 &
b10 #
b10 %
#270
b1001 "
b1001 &
b1000000100 #
b1000000100 %
#280
b11 "
b11 &
b1000 #
b1000 %
#290
b100 "
b100 &
b10000 #
b10000 %
#300
b101 "
b101 &
b101000 #
b101000 %
#310
b110 "
b110 &
b1000000 #
b1000000 %
#320
b111 "
b111 &
b10000000 #
b10000000 %
#330
b1000 "
b1000 &
b100000000 #
b100000000 %
#340
b1001 "
b1001 &
b1000000001 #
b1000000001 %
#350
b0 "
b0 &
1!
b0 #
b0 %
