tiago-vitor-amorim/microondas_SD/Nivel 1/Nivel 2/Entrada de timer e controle/MUX/MUX.v
module MUX( A, B, S, X);
 
    input wire A, B;
    input wire S;
    output wire X;
    wire S0_inv, a1, b1;
    
    not u1( S0_inv, S );
    and u2( a1, S0_inv, A );
    and u3( b1, S, B );
    or  u4( X, a1, b1 );
 
endmodule

tiago-vitor-amorim/Nivel 1/Nivel 2/Entrada de timer e controle/MUX/MUX_tb.v
module MUX_tb;
 
    reg A_tb, B_tb, S_tb;
    wire X_tb;
 
    MUX dut( A_tb, B_tb, S_tb, X_tb);
 
    initial begin
        $dumpfile("MUX_tb.vcd");
        $dumpvars(0, MUX_tb);

        A_tb = 1'b0; B_tb = 1'b0; S_tb = 1'b0; #1
        $display("A = %x, B = %x, S = %x, X = %x", A_tb, B_tb, S_tb, X_tb);
        A_tb = 1'b0; B_tb = 1'b1; S_tb = 1'b0; #1
        $display("A = %x, B = %x, S = %x, X = %x", A_tb, B_tb, S_tb, X_tb);
        A_tb = 1'b1; B_tb = 1'b0; S_tb = 1'b0; #1
        $display("A = %x, B = %x, S = %x, X = %x", A_tb, B_tb, S_tb, X_tb);
        A_tb = 1'b1; B_tb = 1'b1; S_tb = 1'b0; #1
        $display("A = %x, B = %x, S = %x, X = %x", A_tb, B_tb, S_tb, X_tb);
        A_tb = 1'b0; B_tb = 1'b0; S_tb = 1'b1; #1
        $display("A = %x, B = %x, S = %x, X = %x", A_tb, B_tb, S_tb, X_tb);
        A_tb = 1'b0; B_tb = 1'b1; S_tb = 1'b1; #1
        $display("A = %x, B = %x, S = %x, X = %x", A_tb, B_tb, S_tb, X_tb);
        A_tb = 1'b1; B_tb = 1'b0; S_tb = 1'b1; #1
        $display("A = %x, B = %x, S = %x, X = %x", A_tb, B_tb, S_tb, X_tb);
        A_tb = 1'b1; B_tb = 1'b1; S_tb = 1'b1; #1
        $display("A = %x, B = %x, S = %x, X = %x", A_tb, B_tb, S_tb, X_tb);
    end
endmodule

tiago-vitor-amorim/microondas_SD/Nivel 1/Nivel 2/Entrada de timer e controle/MUX/MUX_tb.vcd
$date
	Wed May 11 22:34:53 2022
$end
$version
	Icarus Verilog
$end
$timescale
	1s
$end
$scope module MUX_tb $end
$var wire 1 ! X_tb $end
$var reg 1 " A_tb $end
$var reg 1 # B_tb $end
$var reg 1 $ S_tb $end
$scope module dut $end
$var wire 1 " A $end
$var wire 1 # B $end
$var wire 1 $ S $end
$var wire 1 % S0_inv $end
$var wire 1 ! X $end
$var wire 1 & a1 $end
$var wire 1 ' b1 $end
$upscope $end
$upscope $end
$enddefinitions $end
#0
$dumpvars
0'
0&
1%
0$
0#
0"
0!
$end
#1
1#
#2
1!
1&
0#
1"
#3
1#
#4
0!
0%
0&
1$
0#
0"
#5
1!
1'
1#
#6
0!
0'
0#
1"
#7
1!
1'
1#
