Projeto 2 Final/Projeto2_Microondas/Projeto2_Microondas/microondas_nivel1/encoder_nivel2/nivel3/HDL/contador_7_n_reciclavel.v
module contador_7_n_reciclavel( 
    input wire Clock, Clear,
    output reg saida);

    reg [2:0] contador = 0;
/*
Como clear é ativo em nível alto, é preciso verificar também quando sua borda positiva chega,
além de ser necessário verificar o contador toda vez que a borda positiva do clock chega.
O contador recebe como entrada o clock e o clear, que vem do codificador e é ativado quando 
alguém tecla algum dígito.

Além disso, ele dá um atraso de 40 ms para evitar trepidação quando alguém clicar em alguma tecla.
Esse valor de 40 ms para tornar a saída positiva é dado na verificação "if(contador == 3)". Aqui,
é verificado se contador é igual a 3 porque ele está em um bloco sequencial, então contador será
incrementado para 4 na execução em que contador=3. 
*/ 
    always @(posedge Clock or posedge Clear) 
    begin
        if(Clear) begin
            saida <= 0;
            contador = 0;
        end
        else begin
            if(contador < 7) 
                contador <= contador + 1;
            if(contador == 3) 
                saida <=  1;
            else 
                saida <= 0;
        end
    end
endmodule

Projeto 2 Final/Projeto2_Microondas/Projeto2_Microondas/microondas_nivel1/encoder_nivel2/nivel3/Teste/contador_7_n_reciclavel_tb.v
`timescale 1ns/1ps
`include "../HDL/contador_7_n_reciclavel.v"

module contador_7_n_reciclavel_tb();

reg Clock_tb, Clear_tb;
wire saida_tb;

contador_7_n_reciclavel UUT (.Clock(Clock_tb),.Clear(Clear_tb),.saida(saida_tb));

always #5 Clock_tb = ~Clock_tb; // Troca o sinal do clock a cada 5ns

always #80 Clear_tb = ~Clear_tb; // Troca o sinal do clear a cada 80ns, para testar o funcionamento

initial begin
    $dumpfile("contador_7_n_reciclavel_tb.vcd");
    $dumpvars;
    Clock_tb = 0;
    Clear_tb = 0;
    #300 $finish;
end

always @(posedge Clock_tb) begin
    $display("Clock_tb = %d | Clear_tb = %d | Saida = %d", Clock_tb, Clear_tb, saida_tb);
end
endmodule

Projeto 2 Final/Projeto2_Microondas/Projeto2_Microondas/microondas_nivel1/encoder_nivel2/nivel3/Teste/contador_7_n_reciclavel_tb.vcd
$date
	Sat Jul 23 16:01:39 2022
$end
$version
	Icarus Verilog
$end
$timescale
	1ps
$end
$scope module contador_7_n_reciclavel_tb $end
$var wire 1 ! saida_tb $end
$var reg 1 " Clear_tb $end
$var reg 1 # Clock_tb $end
$scope module UUT $end
$var wire 1 " Clear $end
$var wire 1 # Clock $end
$var reg 3 $ contador [2:0] $end
$var reg 1 ! saida $end
$upscope $end
$upscope $end
$enddefinitions $end
#0
$dumpvars
b0 $
0#
0"
x!
$end
#5000
0!
b1 $
1#
#10000
0#
#15000
b10 $
1#
#20000
0#
#25000
b11 $
1#
#30000
0#
#35000
1!
b100 $
1#
#40000
0#
#45000
0!
b101 $
1#
#50000
0#
#55000
b110 $
1#
#60000
0#
#65000
b111 $
1#
#70000
0#
#75000
1#
#80000
b0 $
0#
1"
#85000
1#
#90000
0#
#95000
1#
#100000
0#
#105000
1#
#110000
0#
#115000
1#
#120000
0#
#125000
1#
#130000
0#
#135000
1#
#140000
0#
#145000
1#
#150000
0#
#155000
1#
#160000
0#
0"
#165000
b1 $
1#
#170000
0#
#175000
b10 $
1#
#180000
0#
#185000
b11 $
1#
#190000
0#
#195000
1!
b100 $
1#
#200000
0#
#205000
0!
b101 $
1#
#210000
0#
#215000
b110 $
1#
#220000
0#
#225000
b111 $
1#
#230000
0#
#235000
1#
#240000
b0 $
0#
1"
