Projeto 2 Final/Projeto2_Microondas/Projeto2_Microondas/microondas_nivel1/timer_nivel2/nivel3/HDL/contador_mod_10_min.v
module Counter_mod_10_min(output wire [3:0] ones, 
                      output wire tc,zero, 
                      input wire clk, clearn, EN, loadn, carry_out,
                      input wire [3:0] data, ones_sec);
  // Registradores para que seja possível realizar a atribuição, que é feita de forma sequencial
  // dentro do bloco always
  reg [3:0] current_state;
  assign ones = current_state;
  // O carry_out serve para indicar ao contador dos minutos que é necessário adicionar 1 unidade
  // para que o resultado mostrado no visor seja o certo
  assign zero = (current_state == 0) ? 1 : 0;
  assign tc = ((current_state == 0)& EN) ? 1 : 0;

  // O próximo always verifica a borda de subida do clock e tanto a borda de subida quanto a de 
  // descida do carry_out, para saber quando ele se torna 1 e quando ele se torna 0, para que 
  // seja possível configurar o valor inicial do contador dos minutos de forma correta
  always @(posedge clk or posedge carry_out or negedge carry_out)
    begin
      if (EN) begin
        if (current_state == 4'b0000) begin
          // Se o contador chegar a zero, reinicia a contagem
          current_state <= 4'b1001;
        end
        else begin
          // Se o contador ainda não for 0, diminui em 1 unidade
          current_state <= current_state - 1;
        end
      end
      else begin
        if (!loadn) begin
          // A verificação do carry_out ocorre na condição de carregar o estado inicial do contador
          if (carry_out == 1)
            // Se o carry_out for 1, ele precisa adicionar 1 aos dados
            current_state <= data + 1;
          else
            // Se o carry_out for 0, ele não adiciona 1 aos dados
            current_state <= data;
        end
      end
    end
  // O próximo always verifica o clear de forma assíncrona, para zerar o contador caso a tecla seja
  // apertada
  always @(negedge clearn) begin
    if (!clearn) begin
      current_state <= 4'b0000;
    end
  end
endmodule

Projeto 2 Final/Projeto2_Microondas/Projeto2_Microondas/microondas_nivel1/timer_nivel2/nivel3/HDL/contador_mod_6.v
module Counter_mod_6(output wire [3:0] tens, 
                      output wire tc,zero, carry_out, 
                      input wire clk, clearn, EN, loadn,
                      input wire [3:0] data);

    // Registradores para que seja possível realizar a atribuição, que é feita de forma sequencial
    // dentro do bloco always
    reg [3:0] current_state;
    assign tens = current_state;
    // O carry_out serve para indicar ao contador dos minutos que é necessário adicionar 1 unidade
    // para que o resultado mostrado no visor seja o certo
    reg carry_out_reg;
    assign carry_out = carry_out_reg;

    // O zero só pode ser 1 quando o estado atual desse contador é 0, ou seja, quando ele tiver
    // chegado em 0
    assign zero = (current_state == 0) ? 1 : 0;
    // O tc só pode ser 1 quando o contador tiver chegado a 0 e o enable for 1
    assign tc = ((current_state == 0) & EN) ? 1 : 0;

    always @(posedge clk)
    begin
        if (EN) begin
            if (current_state == 4'b0000) begin
                current_state <= 4'd5;
            end
            else begin
                current_state <= current_state - 1;
            end
        end
        else begin
            if (!loadn) begin
                // O contador verificar se a entrada é maior que 6 quando ele vai receber os 
                // dados pela primeira vez
                if (data > 4'b0101) begin
                    // Se os dados vindos do contador de segundos forem maiores que 5, então é
                    // preciso mudá-los e configurar o carry_out para 1
                    current_state <= data - 6;
                    carry_out_reg <= 1;
                end
                else begin
                    // Se não, ocorre o fluxo normal do contador
                    current_state <= data;
                    carry_out_reg <= 0;
                end
            end
        end
    end
    // O próximo bloco always serve para verificar de forma assíncrona a entrada de limpar os dados
    always @(negedge clearn) begin
        if (!clearn) begin
            current_state <= 4'b0000;
        end
    end

endmodule

Projeto 2 Final/Projeto2_Microondas/Projeto2_Microondas/microondas_nivel1/timer_nivel2/nivel3/HDL/contador_mod_10.v
module Counter_mod_10(output wire [3:0] ones, 
                      output wire tc,zero, 
                      input wire clk, clearn, EN, loadn,
                      input wire [3:0] data);

  // Registradores para que seja possível realizar a atribuição, que é feita de forma sequencial
  // dentro do bloco always
  reg [3:0] current_state;
  assign ones = current_state;
  // O zero só pode ser 1 quando o estado atual desse contador é 0, ou seja, quando ele tiver
  // chegado em 0
  assign zero = (current_state == 0) ? 1 : 0;
  // O tc só pode ser 1 quando o contador tiver chegado a 0 e o enable for 1
  assign tc = ((current_state == 0)& EN) ? 1 : 0;

  always @(posedge clk)
    begin
      if (EN) begin
        if (current_state == 4'b0000) begin
          // Se o contador chegar a zero, reinicia a contagem
          current_state <= 4'b1001;
        end
        else begin
          // Se o contador ainda não for 0, diminui em 1 unidade
          current_state <= current_state - 1;
        end
      end
      else begin
        if (!loadn) begin
          current_state <= data;
        end
      end
    end
  // O próximo always verifica o clear de forma assíncrona, para zerar o contador caso a tecla seja
  // apertada
  always @(negedge clearn) begin
    if (!clearn) begin
      current_state <= 4'b0000;
    end
  end
endmodule

Projeto 2 Final/Projeto2_Microondas/Projeto2_Microondas/microondas_nivel1/timer_nivel2/HDL/timer.v
`include "../nivel3/HDL/contador_mod_6.v"
`include "../nivel3/HDL/contador_mod_10.v"
`include "../nivel3/HDL/contador_mod_10_min.v"

module timer (output wire [3:0] sec_ones, sec_tens, mins, 
    output wire zero, 
    input wire clk, clearn, EN, loadn,
    input wire [3:0] data);

    // Fios internos para realizar as conexões entre os contadores do timer
    wire [3:0] ones_sec, tens, ones_min;
    wire tc_sec, zero_sec, tc_mins, zero_mins, tc_dez, zero_dez;
    wire carry_out; // Bit de carry_out, que serve para saber se o número entrado no campo das 
                    // dezenas de segundos é maior que 5 e, consequentemente, incrementar o 
                    // número dos minutos em 1.

    // unidades dos segundos -> 0,1,2,3,4,5,6,7,8,9
    Counter_mod_10 sec_unit(ones_sec,tc_sec,zero_sec,clk,clearn, EN, loadn, data); 
    // dezenas dos segundos -> 0,1,2,3,4,5,6
    Counter_mod_6 dez_unit(tens,tc_dez,zero_dez, carry_out, clk,clearn,tc_sec,loadn,ones_sec);
    // unidades dos minutos -> 0,1,2,3,4,5,6,7,8,9
    Counter_mod_10_min minutes(ones_min,tc_mins,zero_mins,clk,clearn,tc_dez,loadn, carry_out, tens, ones_sec);

    // Lógica de saída do zero e saídas dos contadores, que vão para o decoder
    assign zero = (zero_dez && zero_mins && zero_sec);
    assign sec_ones = ones_sec;
    assign sec_tens = tens;
    assign mins = ones_min;
    
endmodule

Projeto 2 Final/Projeto2_Microondas/Projeto2_Microondas/microondas_nivel1/timer_nivel2/Teste/timer_tb.v
`timescale 100ms/1ps
`include "../HDL/timer.v"

module timer_tb ();

    reg [3:0] data_tb;
    reg clk_tb, clearn_tb, EN_tb, loadn_tb;
    wire zero;

    // Inteiro i para que seja possível realizar o loop que troca o valor de clk_tb
    integer i;

    timer UUT(.data(data_tb), .clk(clk_tb), .clearn(clearn_tb), .EN(EN_tb), .loadn(loadn_tb));
    

    initial 
    begin
        $dumpfile("timer_tb.vcd");
        $dumpvars;

        // Troca o valor de clk_tb várias vezes a cada 5000ns
        for(i = 0; i < 3005; i=i+1) 
        begin
            #5 clk_tb <= ~clk_tb;
        end
    end


    initial begin
        // Configura o loadn_tb, clearn_tb, clk_tb, EN_tb e data_tb iniciais e depois modifica alguns
        // dos valores
        loadn_tb = 0;
        clearn_tb = 1;
        clk_tb = 1;
        EN_tb = 0;
        data_tb = 4'd5;
        #1
        clearn_tb = 0;
        #1
        clearn_tb = 1;
        #1;
        loadn_tb = 1;
        #1;
        loadn_tb = 0;
        #10;
        loadn_tb = 1;
        #10;
        EN_tb = 1;
    end
    
endmodule

Projeto 2 Final/Projeto2_Microondas/Projeto2_Microondas/microondas_nivel1/timer_nivel2/Teste/timer_tb.vcd
$date
	Sat Jul 23 20:57:04 2022
$end
$version
	Icarus Verilog
$end
$timescale
	1ps
$end
$scope module timer_tb $end
$var reg 1 ! EN_tb $end
$var reg 1 " clearn_tb $end
$var reg 1 # clk_tb $end
$var reg 4 $ data_tb [3:0] $end
$var reg 1 % loadn_tb $end
$var integer 32 & i [31:0] $end
$scope module UUT $end
$var wire 1 ! EN $end
$var wire 1 " clearn $end
$var wire 1 # clk $end
$var wire 4 ' data [3:0] $end
$var wire 1 % loadn $end
$var wire 4 ( mins [3:0] $end
$var wire 4 ) sec_ones [3:0] $end
$var wire 4 * sec_tens [3:0] $end
$var wire 1 + zero $end
$var wire 1 , zero_sec $end
$var wire 1 - zero_mins $end
$var wire 1 . zero_dez $end
$var wire 4 / tens [3:0] $end
$var wire 1 0 tc_sec $end
$var wire 1 1 tc_mins $end
$var wire 1 2 tc_dez $end
$var wire 4 3 ones_sec [3:0] $end
$var wire 4 4 ones_min [3:0] $end
$var wire 1 5 carry_out $end
$scope module dez_unit $end
$var wire 1 5 carry_out $end
$var wire 1 " clearn $end
$var wire 1 # clk $end
$var wire 1 % loadn $end
$var wire 4 6 tens [3:0] $end
$var wire 1 . zero $end
$var wire 1 2 tc $end
$var wire 4 7 data [3:0] $end
$var wire 1 0 EN $end
$var reg 1 8 carry_out_reg $end
$var reg 4 9 current_state [3:0] $end
$upscope $end
$scope module minutes $end
$var wire 1 2 EN $end
$var wire 1 5 carry_out $end
$var wire 1 " clearn $end
$var wire 1 # clk $end
$var wire 4 : data [3:0] $end
$var wire 1 % loadn $end
$var wire 4 ; ones [3:0] $end
$var wire 1 - zero $end
$var wire 1 1 tc $end
$var wire 4 < ones_sec [3:0] $end
$var reg 4 = current_state [3:0] $end
$upscope $end
$scope module sec_unit $end
$var wire 1 ! EN $end
$var wire 1 " clearn $end
$var wire 1 # clk $end
$var wire 4 > data [3:0] $end
$var wire 1 % loadn $end
$var wire 4 ? ones [3:0] $end
$var wire 1 , zero $end
$var wire 1 0 tc $end
$var reg 4 @ current_state [3:0] $end
$upscope $end
$upscope $end
$upscope $end
$enddefinitions $end
#0
$dumpvars
b101 @
b101 ?
b101 >
bx =
b101 <
bx ;
bx :
bx 9
08
b101 7
bx 6
05
bx 4
b101 3
02
01
00
bx /
x.
x-
0,
0+
bx *
b101 )
bx (
b101 '
b0 &
0%
b101 $
1#
1"
0!
$end
#100000000000
1+
1,
1.
1-
b0 )
b0 3
b0 7
b0 <
b0 ?
b0 @
b0 *
b0 /
b0 6
b0 :
b0 9
b0 (
b0 4
b0 ;
b0 =
0"
#200000000000
1"
#300000000000
1%
#400000000000
0%
#500000000000
0#
b1 &
#1000000000000
0+
0,
b101 )
b101 3
b101 7
b101 <
b101 ?
b101 @
1#
b10 &
#1400000000000
1%
#1500000000000
0#
b11 &
#2000000000000
1#
b100 &
#2400000000000
1!
#2500000000000
0#
b101 &
#3000000000000
b100 )
b100 3
b100 7
b100 <
b100 ?
b100 @
1#
b110 &
#3500000000000
0#
b111 &
#4000000000000
b11 )
b11 3
b11 7
b11 <
b11 ?
b11 @
1#
b1000 &
#4500000000000
0#
b1001 &
#5000000000000
b10 )
b10 3
b10 7
b10 <
b10 ?
b10 @
1#
b1010 &
#5500000000000
0#
b1011 &
#6000000000000
b1 )
b1 3
b1 7
b1 <
b1 ?
b1 @
1#
b1100 &
#6500000000000
0#
b1101 &
#7000000000000
11
12
1+
10
1,
b0 )
b0 3
b0 7
b0 <
b0 ?
b0 @
1#
b1110 &
#7500000000000
0#
b1111 &
#8000000000000
0+
00
02
01
0,
0.
0-
b1001 )
b1001 3
b1001 7
b1001 <
b1001 ?
b1001 @
b101 *
b101 /
b101 6
b101 :
b101 9
b1001 (
b1001 4
b1001 ;
b1001 =
1#
b10000 &
#8500000000000
0#
b10001 &
#9000000000000
b1000 )
b1000 3
b1000 7
b1000 <
b1000 ?
b1000 @
1#
b10010 &
#9500000000000
0#
b10011 &
#10000000000000
b111 )
b111 3
b111 7
b111 <
b111 ?
b111 @
1#
b10100 &
#10500000000000
0#
b10101 &
#11000000000000
b110 )
b110 3
b110 7
b110 <
b110 ?
b110 @
1#
b10110 &
#11500000000000
0#
b10111 &
#12000000000000
b101 )
b101 3
b101 7
b101 <
b101 ?
b101 @
1#
b11000 &
#12500000000000
0#
b11001 &
#13000000000000
b100 )
b100 3
b100 7
b100 <
b100 ?
b100 @
1#
b11010 &
#13500000000000
0#
b11011 &
#14000000000000
b11 )
b11 3
b11 7
b11 <
b11 ?
b11 @
1#
b11100 &
#14500000000000
0#
b11101 &
#15000000000000
b10 )
b10 3
b10 7
b10 <
b10 ?
b10 @
1#
b11110 &
#15500000000000
0#
b11111 &
#16000000000000
b1 )
b1 3
b1 7
b1 <
b1 ?
b1 @
1#
b100000 &
#16500000000000
0#
b100001 &
#17000000000000
10
1,
b0 )
b0 3
b0 7
b0 <
b0 ?
b0 @
1#
b100010 &
#17500000000000
0#
b100011 &
#18000000000000
00
0,
b1001 )
b1001 3
b1001 7
b1001 <
b1001 ?
b1001 @
b100 *
b100 /
b100 6
b100 :
b100 9
1#
b100100 &
#18500000000000
0#
b100101 &
#19000000000000
b1000 )
b1000 3
b1000 7
b1000 <
b1000 ?
b1000 @
1#
b100110 &
#19500000000000
0#
b100111 &
#20000000000000
b111 )
b111 3
b111 7
b111 <
b111 ?
b111 @
1#
b101000 &
#20500000000000
0#
b101001 &
#21000000000000
b110 )
b110 3
b110 7
b110 <
b110 ?
b110 @
1#
b101010 &
#21500000000000
0#
b101011 &
#22000000000000
b101 )
b101 3
b101 7
b101 <
b101 ?
b101 @
1#
b101100 &
#22500000000000
0#
b101101 &
#23000000000000
b100 )
b100 3
b100 7
b100 <
b100 ?
b100 @
1#
b101110 &
#23500000000000
0#
b101111 &
#24000000000000
b11 )
b11 3
b11 7
b11 <
b11 ?
b11 @
1#
b110000 &
#24500000000000
0#
b110001 &
#25000000000000
b10 )
b10 3
b10 7
b10 <
b10 ?
b10 @
1#
b110010 &
#25500000000000
0#
b110011 &
#26000000000000
b1 )
b1 3
b1 7
b1 <
b1 ?
b1 @
1#
b110100 &
#26500000000000
0#
b110101 &
#27000000000000
10
1,
b0 )
b0 3
b0 7
b0 <
b0 ?
b0 @
1#
b110110 &
#27500000000000
0#
b110111 &
#28000000000000
00
0,
b1001 )
b1001 3
b1001 7
b1001 <
b1001 ?
b1001 @
b11 *
b11 /
b11 6
b11 :
b11 9
1#
b111000 &
#28500000000000
0#
b111001 &
#29000000000000
b1000 )
b1000 3
b1000 7
b1000 <
b1000 ?
b1000 @
1#
b111010 &
#29500000000000
0#
b111011 &
#30000000000000
b111 )
b111 3
b111 7
b111 <
b111 ?
b111 @
1#
b111100 &
#30500000000000
0#
b111101 &
#31000000000000
b110 )
b110 3
b110 7
b110 <
b110 ?
b110 @
1#
b111110 &
#31500000000000
0#
b111111 &
#32000000000000
b101 )
b101 3
b101 7
b101 <
b101 ?
b101 @
1#
b1000000 &
#32500000000000
0#
b1000001 &
#33000000000000
b100 )
b100 3
b100 7
b100 <
b100 ?
b100 @
1#
b1000010 &
#33500000000000
0#
b1000011 &
#34000000000000
b11 )
b11 3
b11 7
b11 <
b11 ?
b11 @
1#
b1000100 &
#34500000000000
0#
b1000101 &
#35000000000000
b10 )
b10 3
b10 7
b10 <
b10 ?
b10 @
1#
b1000110 &
#35500000000000
0#
b1000111 &
#36000000000000
b1 )
b1 3
b1 7
b1 <
b1 ?
b1 @
1#
b1001000 &
#36500000000000
0#
b1001001 &
#37000000000000
10
1,
b0 )
b0 3
b0 7
b0 <
b0 ?
b0 @
1#
b1001010 &
#37500000000000
0#
b1001011 &
#38000000000000
00
0,
b1001 )
b1001 3
b1001 7
b1001 <
b1001 ?
b1001 @
b10 *
b10 /
b10 6
b10 :
b10 9
1#
b1001100 &
#38500000000000
0#
b1001101 &
#39000000000000
b1000 )
b1000 3
b1000 7
b1000 <
b1000 ?
b1000 @
1#
b1001110 &
#39500000000000
0#
b1001111 &
#40000000000000
b111 )
b111 3
b111 7
b111 <
b111 ?
b111 @
1#
b1010000 &
#40500000000000
0#
b1010001 &
#41000000000000
b110 )
b110 3
b110 7
b110 <
b110 ?
b110 @
1#
b1010010 &
#41500000000000
0#
b1010011 &
#42000000000000
b101 )
b101 3
b101 7
b101 <
b101 ?
b101 @
1#
b1010100 &
#42500000000000
0#
b1010101 &
#43000000000000
b100 )
b100 3
b100 7
b100 <
b100 ?
b100 @
1#
b1010110 &
#43500000000000
0#
b1010111 &
#44000000000000
b11 )
b11 3
b11 7
b11 <
b11 ?
b11 @
1#
b1011000 &
#44500000000000
0#
b1011001 &
#45000000000000
b10 )
b10 3
b10 7
b10 <
b10 ?
b10 @
1#
b1011010 &
#45500000000000
0#
b1011011 &
#46000000000000
b1 )
b1 3
b1 7
b1 <
b1 ?
b1 @
1#
b1011100 &
#46500000000000
0#
b1011101 &
#47000000000000
10
1,
b0 )
b0 3
b0 7
b0 <
b0 ?
b0 @
1#
b1011110 &
#47500000000000
0#
b1011111 &
#48000000000000
00
0,
b1001 )
b1001 3
b1001 7
b1001 <
b1001 ?
b1001 @
b1 *
b1 /
b1 6
b1 :
b1 9
1#
b1100000 &
#48500000000000
0#
b1100001 &
#49000000000000
b1000 )
b1000 3
b1000 7
b1000 <
b1000 ?
b1000 @
1#
b1100010 &
#49500000000000
0#
b1100011 &
#50000000000000
b111 )
b111 3
b111 7
b111 <
b111 ?
b111 @
1#
b1100100 &
#50500000000000
0#
b1100101 &
#51000000000000
b110 )
b110 3
b110 7
b110 <
b110 ?
b110 @
1#
b1100110 &
#51500000000000
0#
b1100111 &
#52000000000000
b101 )
b101 3
b101 7
b101 <
b101 ?
b101 @
1#
b1101000 &
#52500000000000
0#
b1101001 &
#53000000000000
b100 )
b100 3
b100 7
b100 <
b100 ?
b100 @
1#
b1101010 &
#53500000000000
0#
b1101011 &
#54000000000000
b11 )
b11 3
b11 7
b11 <
b11 ?
b11 @
1#
b1101100 &
#54500000000000
0#
b1101101 &
#55000000000000
b10 )
b10 3
b10 7
b10 <
b10 ?
b10 @
1#
b1101110 &
#55500000000000
0#
b1101111 &
#56000000000000
b1 )
b1 3
b1 7
b1 <
b1 ?
b1 @
1#
b1110000 &
#56500000000000
0#
b1110001 &
#57000000000000
10
1,
b0 )
b0 3
b0 7
b0 <
b0 ?
b0 @
1#
b1110010 &
#57500000000000
0#
b1110011 &
#58000000000000
00
02
0,
1.
b1001 )
b1001 3
b1001 7
b1001 <
b1001 ?
b1001 @
b0 *
b0 /
b0 6
b0 :
b0 9
1#
b1110100 &
#58500000000000
0#
b1110101 &
#59000000000000
b1000 )
b1000 3
b1000 7
b1000 <
b1000 ?
b1000 @
1#
b1110110 &
#59500000000000
0#
b1110111 &
#60000000000000
b111 )
b111 3
b111 7
b111 <
b111 ?
b111 @
1#
b1111000 &
#60500000000000
0#
b1111001 &
#61000000000000
b110 )
b110 3
b110 7
b110 <
b110 ?
b110 @
1#
b1111010 &
#61500000000000
0#
b1111011 &
#62000000000000
b101 )
b101 3
b101 7
b101 <
b101 ?
b101 @
1#
b1111100 &
#62500000000000
0#
b1111101 &
#63000000000000
b100 )
b100 3
b100 7
b100 <
b100 ?
b100 @
1#
b1111110 &
#63500000000000
0#
b1111111 &
#64000000000000
b11 )
b11 3
b11 7
b11 <
b11 ?
b11 @
1#
b10000000 &
#64500000000000
0#
b10000001 &
#65000000000000
b10 )
b10 3
b10 7
b10 <
b10 ?
b10 @
1#
b10000010 &
#65500000000000
0#
b10000011 &
#66000000000000
b1 )
b1 3
b1 7
b1 <
b1 ?
b1 @
1#
b10000100 &
#66500000000000
0#
b10000101 &
#67000000000000
12
10
1,
b0 )
b0 3
b0 7
b0 <
b0 ?
b0 @
1#
b10000110 &
#67500000000000
0#
b10000111 &
#68000000000000
00
02
0,
0.
b1001 )
b1001 3
b1001 7
b1001 <
b1001 ?
b1001 @
b101 *
b101 /
b101 6
b101 :
b101 9
b1000 (
b1000 4
b1000 ;
b1000 =
1#
b10001000 &
#68500000000000
0#
b10001001 &
#69000000000000
b1000 )
b1000 3
b1000 7
b1000 <
b1000 ?
b1000 @
1#
b10001010 &
#69500000000000
0#
b10001011 &
#70000000000000
b111 )
b111 3
b111 7
b111 <
b111 ?
b111 @
1#
b10001100 &
#70500000000000
0#
b10001101 &
#71000000000000
b110 )
b110 3
b110 7
b110 <
b110 ?
b110 @
1#
b10001110 &
#71500000000000
0#
b10001111 &
#72000000000000
b101 )
b101 3
b101 7
b101 <
b101 ?
b101 @
1#
b10010000 &
#72500000000000
0#
b10010001 &
#73000000000000
b100 )
b100 3
b100 7
b100 <
b100 ?
b100 @
1#
b10010010 &
#73500000000000
0#
b10010011 &
#74000000000000
b11 )
b11 3
b11 7
b11 <
b11 ?
b11 @
1#
b10010100 &
#74500000000000
0#
b10010101 &
#75000000000000
b10 )
b10 3
b10 7
b10 <
b10 ?
b10 @
1#
b10010110 &
#75500000000000
0#
b10010111 &
#76000000000000
b1 )
b1 3
b1 7
b1 <
b1 ?
b1 @
1#
b10011000 &
#76500000000000
0#
b10011001 &
#77000000000000
10
1,
b0 )
b0 3
b0 7
b0 <
b0 ?
b0 @
1#
b10011010 &
#77500000000000
0#
b10011011 &
#78000000000000
00
0,
b1001 )
b1001 3
b1001 7
b1001 <
b1001 ?
b1001 @
b100 *
b100 /
b100 6
b100 :
b100 9
1#
b10011100 &
#78500000000000
0#
b10011101 &
#79000000000000
b1000 )
b1000 3
b1000 7
b1000 <
b1000 ?
b1000 @
1#
b10011110 &
#79500000000000
0#
b10011111 &
#80000000000000
b111 )
b111 3
b111 7
b111 <
b111 ?
b111 @
1#
b10100000 &
#80500000000000
0#
b10100001 &
#81000000000000
b110 )
b110 3
b110 7
b110 <
b110 ?
b110 @
1#
b10100010 &
#81500000000000
0#
b10100011 &
#82000000000000
b101 )
b101 3
b101 7
b101 <
b101 ?
b101 @
1#
b10100100 &
#82500000000000
0#
b10100101 &
#83000000000000
b100 )
b100 3
b100 7
b100 <
b100 ?
b100 @
1#
b10100110 &
#83500000000000
0#
b10100111 &
#84000000000000
b11 )
b11 3
b11 7
b11 <
b11 ?
b11 @
1#
b10101000 &
#84500000000000
0#
b10101001 &
#85000000000000
b10 )
b10 3
b10 7
b10 <
b10 ?
b10 @
1#
b10101010 &
#85500000000000
0#
b10101011 &
#86000000000000
b1 )
b1 3
b1 7
b1 <
b1 ?
b1 @
1#
b10101100 &
#86500000000000
0#
b10101101 &
#87000000000000
10
1,
b0 )
b0 3
b0 7
b0 <
b0 ?
b0 @
1#
b10101110 &
#87500000000000
0#
b10101111 &
#88000000000000
00
0,
b1001 )
b1001 3
b1001 7
b1001 <
b1001 ?
b1001 @
b11 *
b11 /
b11 6
b11 :
b11 9
1#
b10110000 &
#88500000000000
0#
b10110001 &
#89000000000000
b1000 )
b1000 3
b1000 7
b1000 <
b1000 ?
b1000 @
1#
b10110010 &
#89500000000000
0#
b10110011 &
#90000000000000
b111 )
b111 3
b111 7
b111 <
b111 ?
b111 @
1#
b10110100 &
#90500000000000
0#
b10110101 &
#91000000000000
b110 )
b110 3
b110 7
b110 <
b110 ?
b110 @
1#
b10110110 &
#91500000000000
0#
b10110111 &
#92000000000000
b101 )
b101 3
b101 7
b101 <
b101 ?
b101 @
1#
b10111000 &
#92500000000000
0#
b10111001 &
#93000000000000
b100 )
b100 3
b100 7
b100 <
b100 ?
b100 @
1#
b10111010 &
#93500000000000
0#
b10111011 &
#94000000000000
b11 )
b11 3
b11 7
b11 <
b11 ?
b11 @
1#
b10111100 &
#94500000000000
0#
b10111101 &
#95000000000000
b10 )
b10 3
b10 7
b10 <
b10 ?
b10 @
1#
b10111110 &
#95500000000000
0#
b10111111 &
#96000000000000
b1 )
b1 3
b1 7
b1 <
b1 ?
b1 @
1#
b11000000 &
#96500000000000
0#
b11000001 &
#97000000000000
10
1,
b0 )
b0 3
b0 7
b0 <
b0 ?
b0 @
1#
b11000010 &
#97500000000000
0#
b11000011 &
#98000000000000
00
0,
b1001 )
b1001 3
b1001 7
b1001 <
b1001 ?
b1001 @
b10 *
b10 /
b10 6
b10 :
b10 9
1#
b11000100 &
#98500000000000
0#
b11000101 &
#99000000000000
b1000 )
b1000 3
b1000 7
b1000 <
b1000 ?
b1000 @
1#
b11000110 &
#99500000000000
0#
b11000111 &
#100000000000000
b111 )
b111 3
b111 7
b111 <
b111 ?
b111 @
1#
b11001000 &
#100500000000000
0#
b11001001 &
#101000000000000
b110 )
b110 3
b110 7
b110 <
b110 ?
b110 @
1#
b11001010 &
#101500000000000
0#
b11001011 &
#102000000000000
b101 )
b101 3
b101 7
b101 <
b101 ?
b101 @
1#
b11001100 &
#102500000000000
0#
b11001101 &
#103000000000000
b100 )
b100 3
b100 7
b100 <
b100 ?
b100 @
1#
b11001110 &
#103500000000000
0#
b11001111 &
#104000000000000
b11 )
b11 3
b11 7
b11 <
b11 ?
b11 @
1#
b11010000 &
#104500000000000
0#
b11010001 &
#105000000000000
b10 )
b10 3
b10 7
b10 <
b10 ?
b10 @
1#
b11010010 &
#105500000000000
0#
b11010011 &
#106000000000000
b1 )
b1 3
b1 7
b1 <
b1 ?
b1 @
1#
b11010100 &
#106500000000000
0#
b11010101 &
#107000000000000
10
1,
b0 )
b0 3
b0 7
b0 <
b0 ?
b0 @
1#
b11010110 &
#107500000000000
0#
b11010111 &
#108000000000000
00
0,
b1001 )
b1001 3
b1001 7
b1001 <
b1001 ?
b1001 @
b1 *
b1 /
b1 6
b1 :
b1 9
1#
b11011000 &
#108500000000000
0#
b11011001 &
#109000000000000
b1000 )
b1000 3
b1000 7
b1000 <
b1000 ?
b1000 @
1#
b11011010 &
#109500000000000
0#
b11011011 &
#110000000000000
b111 )
b111 3
b111 7
b111 <
b111 ?
b111 @
1#
b11011100 &
#110500000000000
0#
b11011101 &
#111000000000000
b110 )
b110 3
b110 7
b110 <
b110 ?
b110 @
1#
b11011110 &
#111500000000000
0#
b11011111 &
#112000000000000
b101 )
b101 3
b101 7
b101 <
b101 ?
b101 @
1#
b11100000 &
#112500000000000
0#
b11100001 &
#113000000000000
b100 )
b100 3
b100 7
b100 <
b100 ?
b100 @
1#
b11100010 &
#113500000000000
0#
b11100011 &
#114000000000000
b11 )
b11 3
b11 7
b11 <
b11 ?
b11 @
1#
b11100100 &
#114500000000000
0#
b11100101 &
#115000000000000
b10 )
b10 3
b10 7
b10 <
b10 ?
b10 @
1#
b11100110 &
#115500000000000
0#
b11100111 &
#116000000000000
b1 )
b1 3
b1 7
b1 <
b1 ?
b1 @
1#
b11101000 &
#116500000000000
0#
b11101001 &
#117000000000000
10
1,
b0 )
b0 3
b0 7
b0 <
b0 ?
b0 @
1#
b11101010 &
#117500000000000
0#
b11101011 &
#118000000000000
00
02
0,
1.
b1001 )
b1001 3
b1001 7
b1001 <
b1001 ?
b1001 @
b0 *
b0 /
b0 6
b0 :
b0 9
1#
b11101100 &
#118500000000000
0#
b11101101 &
#119000000000000
b1000 )
b1000 3
b1000 7
b1000 <
b1000 ?
b1000 @
1#
b11101110 &
#119500000000000
0#
b11101111 &
#120000000000000
b111 )
b111 3
b111 7
b111 <
b111 ?
b111 @
1#
b11110000 &
#120500000000000
0#
b11110001 &
#121000000000000
b110 )
b110 3
b110 7
b110 <
b110 ?
b110 @
1#
b11110010 &
#121500000000000
0#
b11110011 &
#122000000000000
b101 )
b101 3
b101 7
b101 <
b101 ?
b101 @
1#
b11110100 &
#122500000000000
0#
b11110101 &
#123000000000000
b100 )
b100 3
b100 7
b100 <
b100 ?
b100 @
1#
b11110110 &
#123500000000000
0#
b11110111 &
#124000000000000
b11 )
b11 3
b11 7
b11 <
b11 ?
b11 @
1#
b11111000 &
#124500000000000
0#
b11111001 &
#125000000000000
b10 )
b10 3
b10 7
b10 <
b10 ?
b10 @
1#
b11111010 &
#125500000000000
0#
b11111011 &
#126000000000000
b1 )
b1 3
b1 7
b1 <
b1 ?
b1 @
1#
b11111100 &
#126500000000000
0#
b11111101 &
#127000000000000
12
10
1,
b0 )
b0 3
b0 7
b0 <
b0 ?
b0 @
1#
b11111110 &
#127500000000000
0#
b11111111 &
#128000000000000
00
02
0,
0.
b1001 )
b1001 3
b1001 7
b1001 <
b1001 ?
b1001 @
b101 *
b101 /
b101 6
b101 :
b101 9
b111 (
b111 4
b111 ;
b111 =
1#
b100000000 &
#128500000000000
0#
b100000001 &
#129000000000000
b1000 )
b1000 3
b1000 7
b1000 <
b1000 ?
b1000 @
1#
b100000010 &
#129500000000000
0#
b100000011 &
#130000000000000
b111 )
b111 3
b111 7
b111 <
b111 ?
b111 @
1#
b100000100 &
#130500000000000
0#
b100000101 &
#131000000000000
b110 )
b110 3
b110 7
b110 <
b110 ?
b110 @
1#
b100000110 &
#131500000000000
0#
b100000111 &
#132000000000000
b101 )
b101 3
b101 7
b101 <
b101 ?
b101 @
1#
b100001000 &
#132500000000000
0#
b100001001 &
#133000000000000
b100 )
b100 3
b100 7
b100 <
b100 ?
b100 @
1#
b100001010 &
#133500000000000
0#
b100001011 &
#134000000000000
b11 )
b11 3
b11 7
b11 <
b11 ?
b11 @
1#
b100001100 &
#134500000000000
0#
b100001101 &
#135000000000000
b10 )
b10 3
b10 7
b10 <
b10 ?
b10 @
1#
b100001110 &
#135500000000000
0#
b100001111 &
#136000000000000
b1 )
b1 3
b1 7
b1 <
b1 ?
b1 @
1#
b100010000 &
#136500000000000
0#
b100010001 &
#137000000000000
10
1,
b0 )
b0 3
b0 7
b0 <
b0 ?
b0 @
1#
b100010010 &
#137500000000000
0#
b100010011 &
#138000000000000
00
0,
b1001 )
b1001 3
b1001 7
b1001 <
b1001 ?
b1001 @
b100 *
b100 /
b100 6
b100 :
b100 9
1#
b100010100 &
#138500000000000
0#
b100010101 &
#139000000000000
b1000 )
b1000 3
b1000 7
b1000 <
b1000 ?
b1000 @
1#
b100010110 &
#139500000000000
0#
b100010111 &
#140000000000000
b111 )
b111 3
b111 7
b111 <
b111 ?
b111 @
1#
b100011000 &
#140500000000000
0#
b100011001 &
#141000000000000
b110 )
b110 3
b110 7
b110 <
b110 ?
b110 @
1#
b100011010 &
#141500000000000
0#
b100011011 &
#142000000000000
b101 )
b101 3
b101 7
b101 <
b101 ?
b101 @
1#
b100011100 &
#142500000000000
0#
b100011101 &
#143000000000000
b100 )
b100 3
b100 7
b100 <
b100 ?
b100 @
1#
b100011110 &
