microwave_level1/microwave_level1/timer_level2/nivel3/contadormod10.v
//contador mod10
//será usado duas vezes no timer
module contadormod10 (
    //variáveis input
    input wire [3:0] data,
    input wire loadn,
    input wire clrn,
    input wire clk,
    input wire en,

    //variáveis input
    output reg [3:0] ones,
    output reg tc,
    output wire zero
);

initial begin
    tc = 0;
end

always @ (negedge clrn)
begin
    ones = 4'b0000;
end

assign zero = (ones == 4'b0000) ? 1'b1 : 1'b0;

always @ (posedge clk)

begin
    if (en) 
        case (ones)
            4'b1001: begin
                ones <= 4'b1000;
                tc <= 1'b0;
            end
            4'b1000: ones <= 4'b0111; 
            4'b0111: ones <= 4'b0110; 
            4'b0110: ones <= 4'b0101; 
            4'b0101: ones <= 4'b0100; 
            4'b0100: ones <= 4'b0011; 
            4'b0011: ones <= 4'b0010; 
            4'b0010: ones <= 4'b0001; 
            4'b0001: begin 
                ones <= 4'b0000;
                tc <= 1'b1;
            end  
            4'b0000: begin
                ones <= 4'b1001;
                tc <= 1'b0;
            end 
            default: ones <= 4'b0000;
        endcase

    else begin
        tc <= 0;

        if(!loadn)
            ones <= data;
        
    end
end
endmodule

microwave_level1/microwave_level1/timer_level2/nivel3/contadormod10_tb.v
`include "contadormod10.v"
//inclui o módulo do contador no file
module contadormod10_tb();
//vars
reg [3:0] data;
reg loadn, clrn, clk, en;

wire [3:0] ones;
wire tc, zero;

contadormod10 dut (data, loadn, clrn, clk, en, ones, tc, zero);//instancia as varíaveis do contador

initial clk = 0;
always #10 clk = !clk;

initial begin

    assign loadn = 1;
    assign en = 0; 
    assign clrn = 1;
    assign data = 4'b0110;

    #5 assign loadn = 0;

    #5 assign loadn = 1;

    #5 assign en = 1; 

    #400 $finish;
end

initial begin
    $monitor("simtime = %g,data =%b, loadn =%b, clrn =%b, clk =%b, en =%b, ones =%b, tc =%b, zero =%b", $time,data, loadn, clrn, clk, en, ones, tc, zero);
    $dumpfile("contadormod10.vcd");//file para representação de ondas
    $dumpvars(0,contadormod10_tb);
end

endmodule

microwave_level1/microwave_level1/timer_level2/nivel3/contadormod10.vcd
$date
	Thu May 12 13:59:55 2022
$end
$version
	Icarus Verilog
$end
$timescale
	1s
$end
$scope module contadormod10_tb $end
$var wire 1 ! zero $end
$var wire 1 " tc $end
$var wire 4 # ones [3:0] $end
$var reg 1 $ clk $end
$var reg 1 % clrn $end
$var reg 4 & data [3:0] $end
$var reg 1 ' en $end
$var reg 1 ( loadn $end
$scope module dut $end
$var wire 1 $ clk $end
$var wire 1 % clrn $end
$var wire 4 ) data [3:0] $end
$var wire 1 ' en $end
$var wire 1 ( loadn $end
$var wire 1 ! zero $end
$var reg 4 * ones [3:0] $end
$var reg 1 " tc $end
$upscope $end
$upscope $end
$enddefinitions $end
#0
$dumpvars
bx *
b110 )
1(
0'
b110 &
1%
0$
bx #
0"
x!
$end
#5
0(
#10
1(
1$
#15
1'
#20
0$
#30
1!
b0 #
b0 *
1$
#40
0$
#50
0!
b1001 #
b1001 *
1$
#60
0$
#70
b1000 #
b1000 *
1$
#80
0$
#90
b111 #
b111 *
1$
#100
0$
#110
b110 #
b110 *
1$
#120
0$
#130
b101 #
b101 *
1$
#140
0$
#150
b100 #
b100 *
1$
#160
0$
#170
b11 #
b11 *
1$
#180
0$
#190
b10 #
b10 *
1$
#200
0$
#210
b1 #
b1 *
1$
#220
0$
#230
1!
1"
b0 #
b0 *
1$
#240
0$
#250
0!
0"
b1001 #
b1001 *
1$
#260
0$
#270
b1000 #
b1000 *
1$
#280
0$
#290
b111 #
b111 *
1$
#300
0$
#310
b110 #
b110 *
1$
#320
0$
#330
b101 #
b101 *
1$
#340
0$
#350
b100 #
b100 *
1$
#360
0$
#370
b11 #
b11 *
1$
#380
0$
#390
b10 #
b10 *
1$
#400
0$
#410
b1 #
b1 *
1$
