tiago-vitor-amorim/Nivel 1/Nivel 2/Timer de minutos - segundos/Contador_MOD6/contador_MOD6.v
module mod6(
  	output wire [3:0] tens, 
    output wire       tc, zero,
    input wire        clearn, loadn, clock, en,
    input wire  [3:0] data); 
    

    reg [3:0] counter; 
    
    always @(posedge clock, negedge clearn)
        begin
          if (clearn == 1'b0)
              counter <= 0;
            else
              if (en == 1'b0)
                begin
                  if (loadn == 1'b0)
                    counter <= data;
                end
          	  else 
                begin
                  if (counter == 0)
                      counter <= 5;
                  else
                      counter <= counter - 1;

                end 
        end

    assign tc = ((counter == 0) && (en == 1'b1)) ? 1'b1 : 1'b0;

    assign zero = (counter == 0) ? 1'b1 : 1'b0;

    assign tens = counter;

endmodule

tiago-vitor-amorim/Nivel 1/Nivel 2/Timer de minutos - segundos/Contador_MOD6/contador_MOD6_tb.v
`include "contador_MOD6.v"

module mod6_tb();
    reg clock_tb, clearn_tb, loadn_tb, en_tb;
    reg [3:0] data_tb;
    wire [3:0] tens_tb;
    wire tc_tb, zero_tb;
    
    mod6 DUT (.clock(clock_tb), .clearn(clearn_tb), .loadn(loadn_tb), .en(en_tb), .data(data_tb), .tens(tens_tb), .tc(tc_tb), .zero(zero_tb));
    
    integer i;
    
    initial 
        begin

            clock_tb = 0; 
            for (i = 0; i < 200; i = i + 1) 
                #500 clock_tb = ~clock_tb;              

        end
    

    initial
        begin
            
           	$dumpfile("mod6_tb.vcd");
			$dumpvars(0,mod6_tb);

            clearn_tb = 1;
            en_tb = 0;

            loadn_tb = 0;
            data_tb = 2;
            #1000 loadn_tb = 1;

            #9000;

            en_tb = 1;

            #15000;

            en_tb = 0;

            #5000;

            clearn_tb = 0;

            #5000;

            clearn_tb = 1;

            en_tb = 1;

            #15000;
    
            en_tb = 0;

        end
        
endmodule

tiago-vitor-amorim/microondas_SD/Nivel 1/Nivel 2/Timer de minutos - segundos/Contador_MOD6/mod6_tb.vcd
$date
	Fri May 13 01:06:03 2022
$end
$version
	Icarus Verilog
$end
$timescale
	1ms
$end
$scope module mod6_tb $end
$var wire 1 ! tc_tb $end
$var wire 4 " tens_tb [3:0] $end
$var wire 1 # zero_tb $end
$var reg 1 $ clearn_tb $end
$var reg 1 % clock_tb $end
$var reg 4 & data_tb [3:0] $end
$var reg 1 ' en_tb $end
$var integer 32 ( i [31:0] $end
$var reg 1 ) loadn_tb $end
$scope module DUT $end
$var wire 1 * clearn $end
$var wire 1 + clock $end
$var wire 4 , data [3:0] $end
$var wire 1 - en $end
$var wire 1 . loadn $end
$var wire 1 ! tc $end
$var wire 4 / tens [3:0] $end
$var wire 1 # zero $end
$var reg 4 0 counter [3:0] $end
$upscope $end
$upscope $end
$enddefinitions $end
#0
$dumpvars
bx 0
bx /
0.
0-
b10 ,
0+
1*
0)
b0 (
0'
b10 &
0%
1$
x#
bx "
0!
$end
#500
0#
b10 0
b10 "
b10 /
b1 (
1%
1+
#1000
b10 (
0%
0+
1)
1.
#1500
b11 (
1%
1+
#2000
b100 (
0%
0+
#2500
b101 (
1%
1+
#3000
b110 (
0%
0+
#3500
b111 (
1%
1+
#4000
b1000 (
0%
0+
#4500
b1001 (
1%
1+
#5000
b1010 (
0%
0+
#5500
b1011 (
1%
1+
#6000
b1100 (
0%
0+
#6500
b1101 (
1%
1+
#7000
b1110 (
0%
0+
#7500
b1111 (
1%
1+
#8000
b10000 (
0%
0+
#8500
b10001 (
1%
1+
#9000
b10010 (
0%
0+
#9500
b10011 (
1%
1+
#10000
b10100 (
0%
0+
1'
1-
#10500
b1 0
b1 "
b1 /
b10101 (
1%
1+
#11000
b10110 (
0%
0+
#11500
1!
1#
b0 0
b0 "
b0 /
b10111 (
1%
1+
#12000
b11000 (
0%
0+
#12500
0!
0#
b101 0
b101 "
b101 /
b11001 (
1%
1+
#13000
b11010 (
0%
0+
#13500
b100 0
b100 "
b100 /
b11011 (
1%
1+
#14000
b11100 (
0%
0+
#14500
b11 0
b11 "
b11 /
b11101 (
1%
1+
#15000
b11110 (
0%
0+
#15500
b10 0
b10 "
b10 /
b11111 (
1%
1+
#16000
b100000 (
0%
0+
#16500
b1 0
b1 "
b1 /
b100001 (
1%
1+
#17000
b100010 (
0%
0+
#17500
1!
1#
b0 0
b0 "
b0 /
b100011 (
1%
1+
#18000
b100100 (
0%
0+
#18500
0!
0#
b101 0
b101 "
b101 /
b100101 (
1%
1+
#19000
b100110 (
0%
0+
#19500
b100 0
b100 "
b100 /
b100111 (
1%
1+
#20000
b101000 (
0%
0+
#20500
b11 0
b11 "
b11 /
b101001 (
1%
1+
#21000
b101010 (
0%
0+
#21500
b10 0
b10 "
b10 /
b101011 (
1%
1+
#22000
b101100 (
0%
0+
#22500
b1 0
b1 "
b1 /
b101101 (
1%
1+
#23000
b101110 (
0%
0+
#23500
1!
1#
b0 0
b0 "
b0 /
b101111 (
1%
1+
#24000
b110000 (
0%
0+
#24500
0!
0#
b101 0
b101 "
b101 /
b110001 (
1%
1+
#25000
b110010 (
0%
0+
0'
0-
#25500
b110011 (
1%
1+
#26000
b110100 (
0%
0+
#26500
b110101 (
1%
1+
#27000
b110110 (
0%
0+
#27500
b110111 (
1%
1+
#28000
b111000 (
0%
0+
#28500
b111001 (
1%
1+
#29000
b111010 (
0%
0+
#29500
b111011 (
1%
1+
#30000
1#
b0 0
b0 "
b0 /
b111100 (
0%
0+
0$
0*
#30500
b111101 (
1%
1+
#31000
b111110 (
0%
0+
#31500
b111111 (
1%
1+
#32000
b1000000 (
0%
0+
#32500
b1000001 (
1%
1+
#33000
b1000010 (
0%
0+
#33500
b1000011 (
1%
1+
#34000
b1000100 (
0%
0+
#34500
b1000101 (
1%
1+
#35000
1!
b1000110 (
0%
0+
1'
1-
1$
1*
#35500
0!
0#
b101 0
b101 "
b101 /
b1000111 (
1%
1+
#36000
b1001000 (
0%
0+
#36500
b100 0
b100 "
b100 /
b1001001 (
1%
1+
#37000
b1001010 (
0%
0+
#37500
b11 0
b11 "
b11 /
b1001011 (
1%
1+
#38000
b1001100 (
0%
0+
#38500
b10 0
b10 "
b10 /
b1001101 (
1%
1+
#39000
b1001110 (
0%
0+
#39500
b1 0
b1 "
b1 /
b1001111 (
1%
1+
#40000
b1010000 (
0%
0+
#40500
1!
1#
b0 0
b0 "
b0 /
b1010001 (
1%
1+
#41000
b1010010 (
0%
0+
#41500
0!
0#
b101 0
b101 "
b101 /
b1010011 (
1%
1+
#42000
b1010100 (
0%
0+
#42500
b100 0
b100 "
b100 /
b1010101 (
1%
1+
#43000
b1010110 (
0%
0+
#43500
b11 0
b11 "
b11 /
b1010111 (
1%
1+
#44000
b1011000 (
0%
0+
#44500
b10 0
b10 "
b10 /
b1011001 (
1%
1+
#45000
b1011010 (
0%
0+
#45500
b1 0
b1 "
b1 /
b1011011 (
1%
1+
#46000
b1011100 (
0%
0+
#46500
1!
1#
b0 0
b0 "
b0 /
b1011101 (
1%
1+
#47000
b1011110 (
0%
0+
#47500
0!
0#
b101 0
b101 "
b101 /
b1011111 (
1%
1+
#48000
b1100000 (
0%
0+
#48500
b100 0
b100 "
b100 /
b1100001 (
1%
1+
#49000
b1100010 (
0%
0+
#49500
b11 0
b11 "
b11 /
b1100011 (
1%
1+
#50000
b1100100 (
0%
0+
0'
0-
#50500
b1100101 (
1%
1+
#51000
b1100110 (
0%
0+
#51500
b1100111 (
1%
1+
#52000
b1101000 (
0%
0+
#52500
b1101001 (
1%
1+
#53000
b1101010 (
0%
0+
#53500
b1101011 (
1%
1+
#54000
b1101100 (
0%
0+
#54500
b1101101 (
1%
1+
#55000
b1101110 (
0%
0+
#55500
b1101111 (
1%
1+
#56000
b1110000 (
0%
0+
#56500
b1110001 (
1%
1+
#57000
b1110010 (
0%
0+
#57500
b1110011 (
1%
1+
#58000
b1110100 (
0%
0+
#58500
b1110101 (
1%
1+
#59000
b1110110 (
0%
0+
#59500
b1110111 (
1%
1+
#60000
b1111000 (
0%
0+
#60500
b1111001 (
1%
1+
#61000
b1111010 (
0%
0+
#61500
b1111011 (
1%
1+
#62000
b1111100 (
0%
0+
#62500
b1111101 (
1%
1+
#63000
b1111110 (
0%
0+
#63500
b1111111 (
1%
1+
#64000
b10000000 (
0%
0+
#64500
b10000001 (
1%
1+
#65000
b10000010 (
0%
0+
#65500
b10000011 (
1%
1+
#66000
b10000100 (
0%
0+
#66500
b10000101 (
1%
1+
#67000
b10000110 (
0%
0+
#67500
b10000111 (
1%
1+
#68000
b10001000 (
0%
0+
#68500
b10001001 (
1%
1+
#69000
b10001010 (
0%
0+
#69500
b10001011 (
1%
1+
#70000
b10001100 (
0%
0+
#70500
b10001101 (
1%
1+
#71000
b10001110 (
0%
0+
#71500
b10001111 (
1%
1+
#72000
b10010000 (
0%
0+
#72500
b10010001 (
1%
1+
#73000
b10010010 (
0%
0+
#73500
b10010011 (
1%
1+
#74000
b10010100 (
0%
0+
#74500
b10010101 (
1%
1+
#75000
b10010110 (
0%
0+
#75500
b10010111 (
1%
1+
#76000
b10011000 (
0%
0+
#76500
b10011001 (
1%
1+
#77000
b10011010 (
0%
0+
#77500
b10011011 (
1%
1+
#78000
b10011100 (
0%
0+
#78500
b10011101 (
1%
1+
#79000
b10011110 (
0%
0+
#79500
b10011111 (
1%
1+
#80000
b10100000 (
0%
0+
#80500
b10100001 (
1%
1+
#81000
b10100010 (
0%
0+
#81500
b10100011 (
1%
1+
#82000
b10100100 (
0%
0+
#82500
b10100101 (
1%
1+
#83000
b10100110 (
0%
0+
#83500
b10100111 (
1%
1+
#84000
b10101000 (
0%
0+
#84500
b10101001 (
1%
1+
#85000
b10101010 (
0%
0+
#85500
b10101011 (
1%
1+
#86000
b10101100 (
0%
0+
#86500
b10101101 (
1%
1+
#87000
b10101110 (
0%
0+
#87500
b10101111 (
1%
1+
#88000
b10110000 (
0%
0+
#88500
b10110001 (
1%
1+
#89000
b10110010 (
0%
0+
#89500
b10110011 (
1%
1+
#90000
b10110100 (
0%
0+
#90500
b10110101 (
1%
1+
#91000
b10110110 (
0%
0+
#91500
b10110111 (
1%
1+
#92000
b10111000 (
0%
0+
#92500
b10111001 (
1%
1+
#93000
b10111010 (
0%
0+
#93500
b10111011 (
1%
1+
#94000
b10111100 (
0%
0+
#94500
b10111101 (
1%
1+
#95000
b10111110 (
0%
0+
#95500
b10111111 (
1%
1+
#96000
b11000000 (
0%
0+
#96500
b11000001 (
1%
1+
#97000
b11000010 (
0%
0+
#97500
b11000011 (
1%
1+
#98000
b11000100 (
0%
0+
#98500
b11000101 (
1%
1+
#99000
b11000110 (
0%
0+
#99500
b11000111 (
1%
1+
#100000
b11001000 (
0%
0+
